[{"Description":"Level 4 Musculoskeletal Procedures","Charge":"3705.06","Category":"DRG"},{"Description":"Abdominal/Peritoneal/Biliary and Related Procedures","Charge":"1918.95","Category":"DRG"},{"Description":"MAJOR JOINT REPLACEMENT OR REATTACHMENT OF LOWER EXTREMITY W/O MCC","Charge":"9392.75","Category":"Standard"},{"Description":"Level 2 Musculoskeletal Procedures","Charge":"911.22","Category":"DRG"},{"Description":"Level 3 Musculoskeletal Procedures","Charge":"1835.45","Category":"DRG"},{"Description":"Level 1 Nerve Procedures","Charge":"1200.2","Category":"DRG"},{"Description":"Level 1 Laparoscopy and Related Services","Charge":"3113.79","Category":"DRG"}]