[{"Description":"PATHOLOGICAL FRACTURES & MUSCULOSKELET & CONN TISS MALIG W CC","Charge":"6165.76","Category":"Standard"},{"Description":"SPINAL FUSION EXCEPT CERVICAL W/O MCC","Charge":"25188.73","Category":"Standard"},{"Description":"Level 1 ICD and Similar Procedures","Charge":"19801.98","Category":"DRG"},{"Description":"Level 3 Pacemaker and Similar Procedures","Charge":"8320.39","Category":"DRG"},{"Description":"Level 2 Pacemaker and Similar Procedures","Charge":"5884.12","Category":"DRG"},{"Description":"Level 3 Electrophysiologic Procedures","Charge":"15787.44","Category":"DRG"},{"Description":"Level 4 Endovascular Procedures","Charge":"13493.11","Category":"DRG"},{"Description":"Level 3 Endovascular Procedures","Charge":"8658.39","Category":"DRG"},{"Description":"Level 2 Endovascular Procedures","Charge":"3966.24","Category":"DRG"},{"Description":"Level 1 Endovascular Procedures","Charge":"2007.21","Category":"DRG"},{"Description":"Level 5 ENT Procedures","Charge":"3399.17","Category":"DRG"},{"Description":"Level 5 Musculoskeletal Procedures","Charge":"8544.7","Category":"DRG"},{"Description":"Level 4 Musculoskeletal Procedures","Charge":"4221.55","Category":"DRG"},{"Description":" WND DEBRID & SKN GRFT EXC HAND, FOR MUSCULO","Charge":"17976.89","Category":"Standard"},{"Description":"Level 2 Breast/Lymphatic Surgery and Related Procedures","Charge":"3636.56","Category":"DRG"},{"Description":"Level 3 Excision/ Biopsy/ Incision and Drainage","Charge":"1759.26","Category":"DRG"},{"Description":"Level 2 Excision/ Biopsy/ Incision and Drainage","Charge":"996.74","Category":"DRG"},{"Description":"LAPAROSCOPIC CHOLECYSTECTOMY W/O C.D.E. W/O CC/MCC","Charge":"7621.0","Category":"Standard"},{"Description":"CIRRHOSIS & ALCOHOLIC HEPATITIS W MCC","Charge":"10649.27","Category":"Standard"},{"Description":"MALIGNANCY OF HEPATOBILIARY SYSTEM OR PANCREAS W MCC","Charge":"10822.94","Category":"Standard"},{"Description":"DISORDERS OF PANCREAS EXCEPT MALIGNANCY W MCC","Charge":"10284.0","Category":"Standard"},{"Description":"DISORDERS OF PANCREAS EXCEPT MALIGNANCY W CC","Charge":"5152.67","Category":"Standard"},{"Description":" DISORDERS OF LIVER EXCEPT MALIG,CIRR,ALC HEPA W MCC","Charge":"11032.85","Category":"Standard"},{"Description":" DISORDERS OF LIVER EXCEPT MALIG,CIRR,ALC HEPA W CC","Charge":"5360.82","Category":"Standard"},{"Description":"DISORDERS OF THE BILIARY TRACT W MCC","Charge":"10249.73","Category":"Standard"},{"Description":"DISORDERS OF THE BILIARY TRACT W CC","Charge":"5916.83","Category":"Standard"},{"Description":"Level 1 Breast/Lymphatic Surgery and Related Procedures","Charge":"2056.35","Category":"DRG"},{"Description":"REVISION OF HIP OR KNEE REPLACEMENT W CC","Charge":"21970.81","Category":"Standard"},{"Description":"PATHOLOGICAL FRACTURES & MUSCULOSKELET & CONN TISS MALIG W MCC","Charge":"12008.1","Category":"Standard"},{"Description":"MAJOR HIP AND KNEE JOINT REPLACEMENT OR REATTACHMENT OF LOWER EXTREM","Charge":"18920.42","Category":"Standard"},{"Description":"OTHER KIDNEY & URINARY TRACT DIAGNOSES W CC","Charge":"5951.57","Category":"Standard"},{"Description":"MAJOR MALE PELVIC PROCEDURES W/O CC/MCC","Charge":"7997.33","Category":"Standard"},{"Description":"MAJOR HEMATOL/IMMUN DIAG EXC SICKLE CELL CRISIS & COAGUL W MCC","Charge":"16668.42","Category":"Standard"},{"Description":"MAJOR HEMATOL/IMMUN DIAG EXC SICKLE CELL CRISIS & COAGUL W CC","Charge":"7169.81","Category":"Standard"},{"Description":"RED BLOOD CELL DISORDERS W MCC","Charge":"8260.27","Category":"Standard"},{"Description":"RED BLOOD CELL DISORDERS W/O MCC","Charge":"5327.31","Category":"Standard"},{"Description":"COAGULATION DISORDERS","Charge":"14054.03","Category":"Standard"},{"Description":"LYMPHOMA & NON","Charge":"26562.08","Category":"Standard"},{"Description":"LYMPHOMA & NON","Charge":"11862.08","Category":"Standard"},{"Description":"INFECTIOUS & PARASITIC DISEASES W O.R. PROCEDURE W MCC","Charge":"35744.92","Category":"Standard"},{"Description":"INFECTIOUS & PARASITIC DISEASES W O.R. PROCEDURE W CC","Charge":"14761.4","Category":"Standard"},{"Description":"POSTOPERATIVE & POST","Charge":"18602.29","Category":"Standard"},{"Description":"OTHER KIDNEY & URINARY TRACT DIAGNOSES W MCC","Charge":"11351.27","Category":"Standard"},{"Description":"POSTOPERATIVE & POST","Charge":"6002.12","Category":"Standard"},{"Description":"SEPTICEMIA OR SEVERE SEPSIS W MV >96 HOURS","Charge":"54625.32","Category":"Standard"},{"Description":"SEPTICEMIA OR SEVERE SEPSIS W/O MV >96 HOURS W MCC","Charge":"11537.74","Category":"Standard"},{"Description":"EXTENSIVE O.R. PROCEDURE UNRELATED TO PRINCIPAL DIAGNOSIS W CC","Charge":"16171.87","Category":"Standard"},{"Description":"EXTENSIVE O.R. PROCEDURE UNRELATED TO PRINCIPAL DIAGNOSIS W MCC","Charge":"29680.71","Category":"Standard"},{"Description":"SIGNS & SYMPTOMS W/O MCC","Charge":"4144.56","Category":"Standard"},{"Description":"COMPLICATIONS OF TREATMENT W CC","Charge":"6241.61","Category":"Standard"},{"Description":"COMPLICATIONS OF TREATMENT W MCC","Charge":"11307.47","Category":"Standard"},{"Description":"POISONING & TOXIC EFFECTS OF DRUGS W/O MCC","Charge":"3891.83","Category":"Standard"},{"Description":"POISONING & TOXIC EFFECTS OF DRUGS W MCC","Charge":"8525.34","Category":"Standard"},{"Description":"OTHER O.R. PROCEDURES FOR INJURIES W CC","Charge":"12519.26","Category":"Standard"},{"Description":"ALCOHOL/DRUG ABUSE OR DEPENDENCE W/O REHABILITATION THERAPY W/O MCC","Charge":"4149.0","Category":"Standard"},{"Description":"ALCOHOL/DRUG ABUSE OR DEPENDENCE W/O REHABILITATION THERAPY W MCC","Charge":"9434.06","Category":"Standard"},{"Description":"VIRAL ILLNESS W/O MCC","Charge":"4491.73","Category":"Standard"},{"Description":"URINARY STONES W/O ESW LITHOTRIPSY W/O MCC","Charge":"4227.47","Category":"Standard"},{"Description":"KIDNEY & URINARY TRACT INFECTIONS W/O MCC","Charge":"4247.48","Category":"Standard"},{"Description":"KIDNEY & URINARY TRACT INFECTIONS W MCC","Charge":"6138.39","Category":"Standard"},{"Description":"MAJOR JOINT REPLACEMENT OR REATTACHMENT OF LOWER EXTREMITY W/O MCC","Charge":"12459.03","Category":"Standard"},{"Description":"HIP & FEMUR PROCEDURES EXCEPT MAJOR JOINT W MCC","Charge":"19259.88","Category":"Standard"},{"Description":"HIP & FEMUR PROCEDURES EXCEPT MAJOR JOINT W CC","Charge":"12280.74","Category":"Standard"},{"Description":"MAJOR JOINT/LIMB REATTACHMENT PROCEDURE OF UPPER EXTREMITIES","Charge":"15160.19","Category":"Standard"},{"Description":" LOWER EXTREM & HUMER PROC EXCEPT HIP,FOOT,FEMUR W CC","Charge":"13430.16","Category":"Standard"},{"Description":"OTHER MUSCULOSKELET SYS & CONN TISS O.R. PROC W CC","Charge":"12844.42","Category":"Standard"},{"Description":"Level 2 ICD and Similar Procedures","Charge":"28565.4","Category":"DRG"},{"Description":"PATHOLOGICAL FRACTURES & MUSCULOSKELET & CONN TISS MALIG W/O CC/MCC","Charge":"4371.0","Category":"Standard"},{"Description":"MEDICAL BACK PROBLEMS W MCC","Charge":"9054.0","Category":"Standard"},{"Description":"MEDICAL BACK PROBLEMS W/O MCC","Charge":"4886.42","Category":"Standard"},{"Description":" TENDONITIS, MYOSITIS & BURSITIS W/O MCC","Charge":"4427.09","Category":"Standard"},{"Description":" AFTERCARE, MUSCULOSKELETAL SYSTEM & CONNECTIVE TISSUE W CC","Charge":"6336.73","Category":"Standard"},{"Description":" FX, SPRN, STRN & DISL EXCEPT FEMUR, HIP, PELVIS & THIGH W/O MCC","Charge":"4170.08","Category":"Standard"},{"Description":"CELLULITIS W MCC","Charge":"9303.0","Category":"Standard"},{"Description":"CELLULITIS W/O MCC","Charge":"4667.8","Category":"Standard"},{"Description":"O.R. PROCEDURES FOR OBESITY W/O CC/MCC","Charge":"9352.32","Category":"Standard"},{"Description":" SKIN GRAFTS & WOUND DEBRID FOR ENDOC, NUTRIT & METAB DIS W CC","Charge":"11316.18","Category":"Standard"},{"Description":"DIABETES W MCC","Charge":"8099.12","Category":"Standard"},{"Description":"DIABETES W CC","Charge":"5652.71","Category":"Standard"},{"Description":" MISC DISORDERS OF NUTRITION,METABOLISM,FLUIDS/ELECTROLYTES W MCC","Charge":"7748.62","Category":"Standard"},{"Description":" MISC DISORDERS OF NUTRITION,METABOLISM,FLUIDS/ELECTROLYTES W/O MCC","Charge":"3999.79","Category":"Standard"},{"Description":"ENDOCRINE DISORDERS W CC","Charge":"6013.21","Category":"Standard"},{"Description":"KIDNEY & URETER PROCEDURES FOR NEOPLASM W CC","Charge":"12502.92","Category":"Standard"},{"Description":"KIDNEY & URETER PROCEDURES FOR NEOPLASM W/O CC/MCC","Charge":"9322.38","Category":"Standard"},{"Description":"RENAL FAILURE W MCC","Charge":"10262.75","Category":"Standard"},{"Description":"RENAL FAILURE W CC","Charge":"5458.51","Category":"Standard"},{"Description":"RENAL FAILURE W/O CC/MCC","Charge":"3202.76","Category":"Standard"},{"Description":"REVISION OF HIP OR KNEE REPLACEMENT W/O CC/MCC","Charge":"17589.57","Category":"Standard"},{"Description":"Level 2 Upper GI Procedures","Charge":"1092.01","Category":"DRG"},{"Description":"Level 5 Gynecologic Procedures","Charge":"2982.56","Category":"DRG"},{"Description":"Complex GI Procedures","Charge":"3242.55","Category":"DRG"},{"Description":"MAJOR CHEST TRAUMA W CC","Charge":"5397.4","Category":"Standard"},{"Description":"PLEURAL EFFUSION W CC","Charge":"6213.69","Category":"Standard"},{"Description":"PULMONARY EDEMA & RESPIRATORY FAILURE","Charge":"7780.23","Category":"Standard"},{"Description":"CHRONIC OBSTRUCTIVE PULMONARY DISEASE W MCC","Charge":"7101.75","Category":"Standard"},{"Description":"CHRONIC OBSTRUCTIVE PULMONARY DISEASE W CC","Charge":"5363.4","Category":"Standard"},{"Description":"CHRONIC OBSTRUCTIVE PULMONARY DISEASE W/O CC/MCC","Charge":"4162.62","Category":"Standard"},{"Description":"SIMPLE PNEUMONIA & PLEURISY W MCC","Charge":"7874.62","Category":"Standard"},{"Description":"SIMPLE PNEUMONIA & PLEURISY W CC","Charge":"5365.34","Category":"Standard"},{"Description":"SIMPLE PNEUMONIA & PLEURISY W/O CC/MCC","Charge":"3719.89","Category":"Standard"},{"Description":"PNEUMOTHORAX W CC","Charge":"6521.69","Category":"Standard"},{"Description":"BRONCHITIS & ASTHMA W CC/MCC","Charge":"5247.3","Category":"Standard"},{"Description":"RESPIRATORY NEOPLASMS W CC","Charge":"6988.75","Category":"Standard"},{"Description":"RESPIRATORY SYSTEM DIAGNOSIS W VENTILATOR SUPPORT <=96 HOURS","Charge":"15806.95","Category":"Standard"},{"Description":"CARDIAC VALVE & OTH MAJ CARDIOTHORACIC PROC W/O CARD CATH W MCC","Charge":"57537.23","Category":"Standard"},{"Description":"CARDIAC VALVE & OTH MAJ CARDIOTHORACIC PROC W/O CARD CATH W CC","Charge":"32805.31","Category":"Standard"},{"Description":"OTHER CARDIOTHORACIC PROCEDURES W MCC","Charge":"48043.58","Category":"Standard"},{"Description":"OTHER CARDIOTHORACIC PROCEDURES W/O MCC","Charge":"30932.92","Category":"Standard"},{"Description":"CORONARY BYPASS W CARDIAC CATH W MCC","Charge":"47318.96","Category":"Standard"},{"Description":"CORONARY BYPASS W CARDIAC CATH W/O MCC","Charge":"29986.45","Category":"Standard"},{"Description":"CORONARY BYPASS W/O CARDIAC CATH W MCC","Charge":"35097.6","Category":"Standard"},{"Description":"CORONARY BYPASS W/O CARDIAC CATH W/O MCC","Charge":"24039.68","Category":"Standard"},{"Description":"PERMANENT CARDIAC PACEMAKER IMPLANT W MCC","Charge":"22184.18","Category":"Standard"},{"Description":"Level 3 Upper GI Procedures","Charge":"2014.29","Category":"DRG"},{"Description":"PERMANENT CARDIAC PACEMAKER IMPLANT W/O CC/MCC","Charge":"13366.35","Category":"Standard"},{"Description":"CARDIAC VALVE & OTH MAJ CARDIOTHORACIC PROC W CARD CATH W MCC","Charge":"74349.38","Category":"Standard"},{"Description":"RESPIRATORY NEOPLASMS W MCC","Charge":"10704.6","Category":"Standard"},{"Description":"RESPIRATORY INFECTIONS & INFLAMMATIONS W CC","Charge":"7886.35","Category":"Standard"},{"Description":"RESPIRATORY INFECTIONS & INFLAMMATIONS W MCC","Charge":"11669.75","Category":"Standard"},{"Description":" ECMO OR TRACH W MV >96 HRS OR PDX EXC FACE, MOUTH & NECK W MAJ O.R.","Charge":"120436.5","Category":"Standard"},{"Description":"CRANIOTOMY & ENDOVASCULAR INTRACRANIAL PROCEDURES W MCC","Charge":"28205.48","Category":"Standard"},{"Description":"EXTRACRANIAL PROCEDURES W CC","Charge":"10007.17","Category":"Standard"},{"Description":"EXTRACRANIAL PROCEDURES W/O CC/MCC","Charge":"6581.55","Category":"Standard"},{"Description":"NERVOUS SYSTEM NEOPLASMS W MCC","Charge":"8008.53","Category":"Standard"},{"Description":"DEGENERATIVE NERVOUS SYSTEM DISORDERS W MCC","Charge":"13378.8","Category":"Standard"},{"Description":"DEGENERATIVE NERVOUS SYSTEM DISORDERS W/O MCC","Charge":"7044.93","Category":"Standard"},{"Description":"INTRACRANIAL HEMORRHAGE OR CEREBRAL INFARCTION W MCC","Charge":"11118.6","Category":"Standard"},{"Description":"INTRACRANIAL HEMORRHAGE OR CEREBRAL INFARCTION W CC OR TPA IN 24 HRS","Charge":"6096.49","Category":"Standard"},{"Description":"INTRACRANIAL HEMORRHAGE OR CEREBRAL INFARCTION W/O CC/MCC","Charge":"4028.62","Category":"Standard"},{"Description":"TRANSIENT ISCHEMIA","Charge":"4044.64","Category":"Standard"},{"Description":"NONSPECIFIC CEREBROVASCULAR DISORDERS W MCC","Charge":"10755.27","Category":"Standard"},{"Description":"NONSPECIFIC CEREBROVASCULAR DISORDERS W CC","Charge":"5856.62","Category":"Standard"},{"Description":" TRAUMATIC STUPOR & COMA, COMA <1 HR W MCC","Charge":"13216.86","Category":"Standard"},{"Description":" TRAUMATIC STUPOR & COMA, COMA <1 HR W CC","Charge":"6459.88","Category":"Standard"},{"Description":"OTHER DISORDERS OF NERVOUS SYSTEM W MCC","Charge":"9820.07","Category":"Standard"},{"Description":"OTHER DISORDERS OF NERVOUS SYSTEM W CC","Charge":"5502.18","Category":"Standard"},{"Description":"SEIZURES W MCC","Charge":"9901.33","Category":"Standard"},{"Description":"SEIZURES W/O MCC","Charge":"5274.7","Category":"Standard"},{"Description":"MAJOR CHEST PROCEDURES W CC","Charge":"15320.82","Category":"Standard"},{"Description":"MAJOR CHEST PROCEDURES W/O CC/MCC","Charge":"10927.75","Category":"Standard"},{"Description":"OTHER RESP SYSTEM O.R. PROCEDURES W MCC","Charge":"27386.65","Category":"Standard"},{"Description":"OTHER RESP SYSTEM O.R. PROCEDURES W CC","Charge":"12481.82","Category":"Standard"},{"Description":"PULMONARY EMBOLISM W MCC","Charge":"8987.9","Category":"Standard"},{"Description":"PULMONARY EMBOLISM W/O MCC","Charge":"5178.43","Category":"Standard"},{"Description":"PERC CARDIOVASC PROC W DRUG","Charge":"21431.23","Category":"Standard"},{"Description":"PERC CARDIOVASC PROC W DRUG","Charge":"13023.88","Category":"Standard"},{"Description":"PERMANENT CARDIAC PACEMAKER IMPLANT W CC","Charge":"15998.0","Category":"Standard"},{"Description":"OTHER VASCULAR PROCEDURES W CC","Charge":"17024.62","Category":"Standard"},{"Description":"HERNIA PROCEDURES EXCEPT INGUINAL & FEMORAL W CC","Charge":"10625.95","Category":"Standard"},{"Description":"OTHER VASCULAR PROCEDURES W MCC","Charge":"24551.95","Category":"Standard"},{"Description":"MAJOR GASTROINTESTINAL DISORDERS & PERITONEAL INFECTIONS W MCC","Charge":"15367.5","Category":"Standard"},{"Description":"MAJOR GASTROINTESTINAL DISORDERS & PERITONEAL INFECTIONS W CC","Charge":"6505.21","Category":"Standard"},{"Description":"DIGESTIVE MALIGNANCY W CC","Charge":"7320.07","Category":"Standard"},{"Description":"G.I. HEMORRHAGE W MCC","Charge":"11590.49","Category":"Standard"},{"Description":"G.I. HEMORRHAGE W CC","Charge":"5974.63","Category":"Standard"},{"Description":"COMPLICATED PEPTIC ULCER W CC","Charge":"6770.82","Category":"Standard"},{"Description":"G.I. OBSTRUCTION W MCC","Charge":"10734.33","Category":"Standard"},{"Description":"G.I. OBSTRUCTION W CC","Charge":"4963.18","Category":"Standard"},{"Description":"G.I. OBSTRUCTION W/O CC/MCC","Charge":"3089.43","Category":"Standard"},{"Description":" ESOPHAGITIS, GASTROENT & MISC DIGEST DISORDERS W MCC","Charge":"8626.44","Category":"Standard"},{"Description":" ESOPHAGITIS, GASTROENT & MISC DIGEST DISORDERS W/O MCC","Charge":"4064.34","Category":"Standard"},{"Description":"OTHER DIGESTIVE SYSTEM DIAGNOSES W MCC","Charge":"10591.77","Category":"Standard"},{"Description":"OTHER DIGESTIVE SYSTEM DIAGNOSES W CC","Charge":"5654.9","Category":"Standard"},{"Description":"LAPAROSCOPIC CHOLECYSTECTOMY W/O C.D.E. W CC","Charge":"10002.69","Category":"Standard"},{"Description":"Comprehensive Observation Services","Charge":"1808.65","Category":"DRG"},{"Description":"Level 6 Gynecologic Procedures","Charge":"4728.01","Category":"DRG"},{"Description":"ACUTE ADJUSTMENT REACTION & PSYCHOSOCIAL DYSFUNCTION","Charge":"4251.79","Category":"Standard"},{"Description":"Level 5 Urology and Related Services","Charge":"2828.6","Category":"DRG"},{"Description":"Level 4 Urology and Related Services","Charge":"2087.35","Category":"DRG"},{"Description":"Level 3 Urology and Related Services","Charge":"1346.79","Category":"DRG"},{"Description":"Level 2 Laparoscopy and Related Services","Charge":"5868.76","Category":"DRG"},{"Description":"Level 1 Laparoscopy and Related Services","Charge":"3426.69","Category":"DRG"},{"Description":"Abdominal/Peritoneal/Biliary and Related Procedures","Charge":"2232.7","Category":"DRG"},{"Description":"MAJOR SMALL & LARGE BOWEL PROCEDURES W/O CC/MCC","Charge":"10074.85","Category":"Standard"},{"Description":"MAJOR SMALL & LARGE BOWEL PROCEDURES W CC","Charge":"16809.95","Category":"Standard"},{"Description":"HERNIA PROCEDURES EXCEPT INGUINAL & FEMORAL W/O CC/MCC","Charge":"7574.85","Category":"Standard"},{"Description":" STOMACH, ESOPHAGEAL & DUODENAL PROC W/O CC/MCC","Charge":"8402.73","Category":"Standard"},{"Description":"OTHER VASCULAR PROCEDURES W/O CC/MCC","Charge":"11221.88","Category":"Standard"},{"Description":"ENDOVASCULAR CARDIAC VALVE REPLACEMENT W MCC","Charge":"53657.0","Category":"Standard"},{"Description":"ENDOVASCULAR CARDIAC VALVE REPLACEMENT W/O MCC","Charge":"40949.46","Category":"Standard"},{"Description":"AORTIC AND HEART ASSIST PROCEDURES EXCEPT PULSATION BALLOON W/O MCC","Charge":"26068.79","Category":"Standard"},{"Description":"OTHER MAJOR CARDIOVASCULAR PROCEDURES W CC","Charge":"20222.31","Category":"Standard"},{"Description":"PERCUTANEOUS INTRACARDIAC PROCEDURES W/O MCC","Charge":"15976.42","Category":"Standard"},{"Description":" ACUTE MYOCARDIAL INFARCTION, DISCHARGED ALIVE W MCC","Charge":"10082.98","Category":"Standard"},{"Description":" ACUTE MYOCARDIAL INFARCTION, DISCHARGED ALIVE W CC","Charge":"5894.21","Category":"Standard"},{"Description":"MAJOR SMALL & LARGE BOWEL PROCEDURES W MCC","Charge":"36199.84","Category":"Standard"},{"Description":" ACUTE MYOCARDIAL INFARCTION, EXPIRED W MCC","Charge":"11706.73","Category":"Standard"},{"Description":" CIRCULATORY DISORDERS EXCEPT AMI, W CARD CATH W MCC","Charge":"14014.67","Category":"Standard"},{"Description":" CIRCULATORY DISORDERS EXCEPT AMI, W CARD CATH W/O MCC","Charge":"6981.89","Category":"Standard"},{"Description":" ACUTE MYOCARDIAL INFARCTION, DISCHARGED ALIVE W/O CC/MCC","Charge":"3707.17","Category":"Standard"},{"Description":"HEART FAILURE & SHOCK W CC","Charge":"5545.88","Category":"Standard"},{"Description":"OTHER CIRCULATORY SYSTEM DIAGNOSES W CC","Charge":"5544.41","Category":"Standard"},{"Description":"HEART FAILURE & SHOCK W MCC","Charge":"9300.8","Category":"Standard"},{"Description":"CHEST PAIN","Charge":"3828.17","Category":"Standard"},{"Description":"SYNCOPE & COLLAPSE","Charge":"4617.63","Category":"Standard"},{"Description":"CARDIAC ARRHYTHMIA & CONDUCTION DISORDERS W/O CC/MCC","Charge":"2897.19","Category":"Standard"},{"Description":"OTHER CIRCULATORY SYSTEM DIAGNOSES W MCC","Charge":"15708.0","Category":"Standard"},{"Description":"CARDIAC ARRHYTHMIA & CONDUCTION DISORDERS W MCC","Charge":"7513.0","Category":"Standard"},{"Description":"HYPERTENSION W/O MCC","Charge":"3736.15","Category":"Standard"},{"Description":"HYPERTENSION W MCC","Charge":"6221.69","Category":"Standard"},{"Description":"PERIPHERAL VASCULAR DISORDERS W CC","Charge":"6021.53","Category":"Standard"},{"Description":"HEART FAILURE & SHOCK W/O CC/MCC","Charge":"3758.19","Category":"Standard"},{"Description":"CARDIAC ARRHYTHMIA & CONDUCTION DISORDERS W CC","Charge":"4614.58","Category":"Standard"},{"Description":"SEPTICEMIA OR SEVERE SEPSIS W/O MV >96 HOURS W/O MCC","Charge":"6017.3","Category":"Standard"}]