[{"Description": " EXTENSIVE O.R. PROCEDURE UNRELATED TO PRINCIPAL DIAGNOSIS W MCC", "Charge": "35849.64", "Category": "Standard"}, {"Description": " OTHER MAJOR CARDIOVASCULAR PROCEDURES W CC", "Charge": "18979.27", "Category": "Standard"}, {"Description": " SIGNS & SYMPTOMS W MCC", "Charge": "7616.45", "Category": "Standard"}, {"Description": " BRONCHITIS & ASTHMA W CC/MCC", "Charge": "6088.24", "Category": "Standard"}, {"Description": " BRONCHITIS & ASTHMA W/O CC/MCC", "Charge": "4075.13", "Category": "Standard"}, {"Description": " RESPIRATORY SYSTEM DIAGNOSIS W VENTILATOR SUPPORT <=96 HOURS", "Charge": "16365.05", "Category": "Standard"}, {"Description": " PERMANENT CARDIAC PACEMAKER IMPLANT W MCC", "Charge": "21844.14", "Category": "Standard"}, {"Description": " PERMANENT CARDIAC PACEMAKER IMPLANT W CC", "Charge": "17916.57", "Category": "Standard"}, {"Description": " PERMANENT CARDIAC PACEMAKER IMPLANT W/O CC/MCC", "Charge": "14369.53", "Category": "Standard"}, {"Description": " PERC CARDIOVASC PROC W DRUG", "Charge": "23895.65", "Category": "Standard"}, {"Description": " PERC CARDIOVASC PROC W DRUG", "Charge": "13964.73", "Category": "Standard"}, {"Description": " OTHER VASCULAR PROCEDURES W MCC", "Charge": "29133.36", "Category": "Standard"}, {"Description": " OTHER VASCULAR PROCEDURES W CC", "Charge": "18959.24", "Category": "Standard"}, {"Description": " OTHER MAJOR CARDIOVASCULAR PROCEDURES W MCC", "Charge": "37086.89", "Category": "Standard"}, {"Description": " ACUTE MYOCARDIAL INFARCTION, DISCHARGED ALIVE W MCC", "Charge": "10853.77", "Category": "Standard"}, {"Description": " ACUTE MYOCARDIAL INFARCTION, DISCHARGED ALIVE W CC", "Charge": "6327.68", "Category": "Standard"}, {"Description": " SIMPLE PNEUMONIA & PLEURISY W/O CC/MCC", "Charge": "4189.33", "Category": "Standard"}, {"Description": " ACUTE MYOCARDIAL INFARCTION, DISCHARGED ALIVE W/O CC/MCC", "Charge": "4665.29", "Category": "Standard"}, {"Description": " CIRCULATORY DISORDERS EXCEPT AMI, W CARD CATH W/O MCC", "Charge": "7024.27", "Category": "Standard"}, {"Description": " HEART FAILURE & SHOCK W MCC", "Charge": "9615.78", "Category": "Standard"}, {"Description": " HEART FAILURE & SHOCK W CC", "Charge": "6149.27", "Category": "Standard"}, {"Description": " HEART FAILURE & SHOCK W/O CC/MCC", "Charge": "4163.18", "Category": "Standard"}, {"Description": " PERIPHERAL VASCULAR DISORDERS W MCC", "Charge": "9047.09", "Category": "Standard"}, {"Description": " PERIPHERAL VASCULAR DISORDERS W CC", "Charge": "6657.6", "Category": "Standard"}, {"Description": " HYPERTENSION W/O MCC", "Charge": "3924.38", "Category": "Standard"}, {"Description": " CARDIAC ARRHYTHMIA & CONDUCTION DISORDERS W CC", "Charge": "4901.69", "Category": "Standard"}, {"Description": " CARDIAC ARRHYTHMIA & CONDUCTION DISORDERS W/O CC/MCC", "Charge": "3329.13", "Category": "Standard"}, {"Description": " SYNCOPE & COLLAPSE", "Charge": "4518.27", "Category": "Standard"}, {"Description": " CHEST PAIN", "Charge": "4060.28", "Category": "Standard"}, {"Description": " OTHER CIRCULATORY SYSTEM DIAGNOSES W MCC", "Charge": "13542.0", "Category": "Standard"}, {"Description": " MAJOR SMALL & LARGE BOWEL PROCEDURES W MCC", "Charge": "43011.15", "Category": "Standard"}, {"Description": " CIRCULATORY DISORDERS EXCEPT AMI, W CARD CATH W MCC", "Charge": "13680.82", "Category": "Standard"}, {"Description": " MAJOR SMALL & LARGE BOWEL PROCEDURES W CC", "Charge": "16228.84", "Category": "Standard"}, {"Description": " SIMPLE PNEUMONIA & PLEURISY W CC", "Charge": "5986.02", "Category": "Standard"}, {"Description": " CHRONIC OBSTRUCTIVE PULMONARY DISEASE W/O CC/MCC", "Charge": "4123.35", "Category": "Standard"}, {"Description": " EXTRACRANIAL PROCEDURES W CC", "Charge": "10521.27", "Category": "Standard"}, {"Description": " EXTRACRANIAL PROCEDURES W/O CC/MCC", "Charge": "6486.0", "Category": "Standard"}, {"Description": " DEGENERATIVE NERVOUS SYSTEM DISORDERS W/O MCC", "Charge": "7233.98", "Category": "Standard"}, {"Description": " INTRACRANIAL HEMORRHAGE OR CEREBRAL INFARCTION W MCC", "Charge": "12479.92", "Category": "Standard"}, {"Description": " INTRACRANIAL HEMORRHAGE OR CEREBRAL INFARCTION W CC OR TPA IN 24 HRS", "Charge": "6512.99", "Category": "Standard"}, {"Description": " INTRACRANIAL HEMORRHAGE OR CEREBRAL INFARCTION W/O CC/MCC", "Charge": "4184.4", "Category": "Standard"}, {"Description": " TRANSIENT ISCHEMIA", "Charge": "4675.71", "Category": "Standard"}, {"Description": " CRANIAL & PERIPHERAL NERVE DISORDERS W/O MCC", "Charge": "5982.4", "Category": "Standard"}, {"Description": " TRAUMATIC STUPOR & COMA, COMA <1 HR W CC", "Charge": "7523.2", "Category": "Standard"}, {"Description": " TRAUMATIC STUPOR & COMA, COMA <1 HR W/O CC/MCC", "Charge": "5130.93", "Category": "Standard"}, {"Description": " OTHER DISORDERS OF NERVOUS SYSTEM W CC", "Charge": "5806.31", "Category": "Standard"}, {"Description": " SEIZURES W MCC", "Charge": "10835.25", "Category": "Standard"}, {"Description": " SEIZURES W/O MCC", "Charge": "5552.96", "Category": "Standard"}, {"Description": " SIMPLE PNEUMONIA & PLEURISY W MCC", "Charge": "9209.31", "Category": "Standard"}, {"Description": " DYSEQUILIBRIUM", "Charge": "4242.0", "Category": "Standard"}, {"Description": " MAJOR CHEST PROCEDURES W CC", "Charge": "15898.45", "Category": "Standard"}, {"Description": " MAJOR CHEST PROCEDURES W/O CC/MCC", "Charge": "11477.35", "Category": "Standard"}, {"Description": " PULMONARY EMBOLISM W MCC", "Charge": "10280.19", "Category": "Standard"}, {"Description": " PULMONARY EMBOLISM W/O MCC", "Charge": "6132.29", "Category": "Standard"}, {"Description": " RESPIRATORY INFECTIONS & INFLAMMATIONS W MCC", "Charge": "12514.03", "Category": "Standard"}, {"Description": " RESPIRATORY INFECTIONS & INFLAMMATIONS W CC", "Charge": "8897.67", "Category": "Standard"}, {"Description": " RESPIRATORY NEOPLASMS W MCC", "Charge": "11681.94", "Category": "Standard"}, {"Description": " RESPIRATORY NEOPLASMS W CC", "Charge": "7030.47", "Category": "Standard"}, {"Description": " PLEURAL EFFUSION W MCC", "Charge": "10097.0", "Category": "Standard"}, {"Description": " PLEURAL EFFUSION W CC", "Charge": "7820.0", "Category": "Standard"}, {"Description": " PULMONARY EDEMA & RESPIRATORY FAILURE", "Charge": "8401.18", "Category": "Standard"}, {"Description": " CHRONIC OBSTRUCTIVE PULMONARY DISEASE W MCC", "Charge": "7205.22", "Category": "Standard"}, {"Description": " CHRONIC OBSTRUCTIVE PULMONARY DISEASE W CC", "Charge": "5861.38", "Category": "Standard"}, {"Description": " MAJOR CHEST PROCEDURES W MCC", "Charge": "30989.27", "Category": "Standard"}, {"Description": " MAJOR SMALL & LARGE BOWEL PROCEDURES W/O CC/MCC", "Charge": "11264.61", "Category": "Standard"}, {"Description": " MAJOR GASTROINTESTINAL DISORDERS & PERITONEAL INFECTIONS W CC", "Charge": "7224.04", "Category": "Standard"}, {"Description": " DIGESTIVE MALIGNANCY W CC", "Charge": "8115.45", "Category": "Standard"}, {"Description": " MISC DISORDERS OF NUTRITION,METABOLISM,FLUIDS/ELECTROLYTES W/O MCC", "Charge": "4720.72", "Category": "Standard"}, {"Description": " ENDOCRINE DISORDERS W CC", "Charge": "6229.91", "Category": "Standard"}, {"Description": " KIDNEY & URETER PROCEDURES FOR NEOPLASM W CC", "Charge": "13556.91", "Category": "Standard"}, {"Description": " TRANSURETHRAL PROCEDURES W CC", "Charge": "8962.31", "Category": "Standard"}, {"Description": " RENAL FAILURE W MCC", "Charge": "10432.93", "Category": "Standard"}, {"Description": " RENAL FAILURE W CC", "Charge": "5917.39", "Category": "Standard"}, {"Description": " RENAL FAILURE W/O CC/MCC", "Charge": "3830.93", "Category": "Standard"}, {"Description": " KIDNEY & URINARY TRACT INFECTIONS W MCC", "Charge": "6888.6", "Category": "Standard"}, {"Description": " KIDNEY & URINARY TRACT INFECTIONS W/O MCC", "Charge": "4697.56", "Category": "Standard"}, {"Description": " URINARY STONES W/O ESW LITHOTRIPSY W/O MCC", "Charge": "4581.77", "Category": "Standard"}, {"Description": " OTHER KIDNEY & URINARY TRACT DIAGNOSES W MCC", "Charge": "10281.97", "Category": "Standard"}, {"Description": " OTHER KIDNEY & URINARY TRACT DIAGNOSES W CC", "Charge": "6975.89", "Category": "Standard"}, {"Description": " MAJOR MALE PELVIC PROCEDURES W/O CC/MCC", "Charge": "8453.86", "Category": "Standard"}, {"Description": " MISC DISORDERS OF NUTRITION,METABOLISM,FLUIDS/ELECTROLYTES W MCC", "Charge": "7688.47", "Category": "Standard"}, {"Description": " UTERINE & ADNEXA PROC FOR NON", "Charge": "6384.82", "Category": "Standard"}, {"Description": " RED BLOOD CELL DISORDERS W MCC", "Charge": "8998.69", "Category": "Standard"}, {"Description": " RED BLOOD CELL DISORDERS W/O MCC", "Charge": "5645.85", "Category": "Standard"}, {"Description": " COAGULATION DISORDERS", "Charge": "14558.92", "Category": "Standard"}, {"Description": " INFECTIOUS & PARASITIC DISEASES W O.R. PROCEDURE W MCC", "Charge": "41021.38", "Category": "Standard"}, {"Description": " INFECTIOUS & PARASITIC DISEASES W O.R. PROCEDURE W CC", "Charge": "16802.25", "Category": "Standard"}, {"Description": " FEVER", "Charge": "5554.11", "Category": "Standard"}, {"Description": " SEPTICEMIA OR SEVERE SEPSIS W MV >96 HOURS", "Charge": "42165.82", "Category": "Standard"}, {"Description": " SEPTICEMIA OR SEVERE SEPSIS W/O MV >96 HOURS W MCC", "Charge": "12214.59", "Category": "Standard"}, {"Description": " SEPTICEMIA OR SEVERE SEPSIS W/O MV >96 HOURS W/O MCC", "Charge": "6456.94", "Category": "Standard"}, {"Description": " ORGANIC DISTURBANCES & INTELLECTUAL DISABILITY", "Charge": "7548.69", "Category": "Standard"}, {"Description": " ALCOHOL/DRUG ABUSE OR DEPENDENCE W/O REHABILITATION THERAPY W/O MCC", "Charge": "4455.21", "Category": "Standard"}, {"Description": " POISONING & TOXIC EFFECTS OF DRUGS W MCC", "Charge": "9565.28", "Category": "Standard"}, {"Description": " POISONING & TOXIC EFFECTS OF DRUGS W/O MCC", "Charge": "4613.47", "Category": "Standard"}, {"Description": " MAJOR HEMATOL/IMMUN DIAG EXC SICKLE CELL CRISIS & COAGUL W CC", "Charge": "7891.93", "Category": "Standard"}, {"Description": " DIABETES W CC", "Charge": "5049.21", "Category": "Standard"}, {"Description": " DIABETES W MCC", "Charge": "11324.36", "Category": "Standard"}, {"Description": " CELLULITIS W/O MCC", "Charge": "5336.72", "Category": "Standard"}, {"Description": " G.I. HEMORRHAGE W MCC", "Charge": "11958.23", "Category": "Standard"}, {"Description": " G.I. HEMORRHAGE W CC", "Charge": "6138.32", "Category": "Standard"}, {"Description": " G.I. HEMORRHAGE W/O CC/MCC", "Charge": "3348.07", "Category": "Standard"}, {"Description": " G.I. OBSTRUCTION W MCC", "Charge": "11599.0", "Category": "Standard"}, {"Description": " G.I. OBSTRUCTION W CC", "Charge": "5665.98", "Category": "Standard"}, {"Description": " G.I. OBSTRUCTION W/O CC/MCC", "Charge": "3606.37", "Category": "Standard"}, {"Description": " ESOPHAGITIS, GASTROENT & MISC DIGEST DISORDERS W MCC", "Charge": "8043.1", "Category": "Standard"}, {"Description": " ESOPHAGITIS, GASTROENT & MISC DIGEST DISORDERS W/O MCC", "Charge": "4516.27", "Category": "Standard"}, {"Description": " OTHER DIGESTIVE SYSTEM DIAGNOSES W MCC", "Charge": "11779.53", "Category": "Standard"}, {"Description": " OTHER DIGESTIVE SYSTEM DIAGNOSES W CC", "Charge": "6142.78", "Category": "Standard"}, {"Description": " OTHER DIGESTIVE SYSTEM DIAGNOSES W/O CC/MCC", "Charge": "3822.13", "Category": "Standard"}, {"Description": " LAPAROSCOPIC CHOLECYSTECTOMY W/O C.D.E. W/O CC/MCC", "Charge": "8468.35", "Category": "Standard"}, {"Description": " MALIGNANCY OF HEPATOBILIARY SYSTEM OR PANCREAS W MCC", "Charge": "12050.82", "Category": "Standard"}, {"Description": " DISORDERS OF THE BILIARY TRACT W MCC", "Charge": "11206.0", "Category": "Standard"}, {"Description": " DISORDERS OF THE BILIARY TRACT W CC", "Charge": "6463.25", "Category": "Standard"}, {"Description": " SPINAL FUSION EXCEPT CERVICAL W/O MCC", "Charge": "27881.81", "Category": "Standard"}, {"Description": " MAJOR JOINT REPLACEMENT OR REATTACHMENT OF LOWER EXTREMITY W/O MCC", "Charge": "13502.03", "Category": "Standard"}, {"Description": " HIP & FEMUR PROCEDURES EXCEPT MAJOR JOINT W MCC", "Charge": "20418.05", "Category": "Standard"}, {"Description": " HIP & FEMUR PROCEDURES EXCEPT MAJOR JOINT W CC", "Charge": "13662.11", "Category": "Standard"}, {"Description": " MAJOR JOINT/LIMB REATTACHMENT PROCEDURE OF UPPER EXTREMITIES", "Charge": "16457.73", "Category": "Standard"}, {"Description": " FRACTURES OF HIP & PELVIS W/O MCC", "Charge": "4476.5", "Category": "Standard"}, {"Description": " PATHOLOGICAL FRACTURES & MUSCULOSKELET & CONN TISS MALIG W CC", "Charge": "7193.69", "Category": "Standard"}, {"Description": " PATHOLOGICAL FRACTURES & MUSCULOSKELET & CONN TISS MALIG W/O CC/MCC", "Charge": "4756.25", "Category": "Standard"}, {"Description": " MEDICAL BACK PROBLEMS W/O MCC", "Charge": "5492.5", "Category": "Standard"}, {"Description": " BONE DISEASES & ARTHROPATHIES W/O MCC", "Charge": "4596.93", "Category": "Standard"}, {"Description": " SIGNS & SYMPTOMS OF MUSCULOSKELETAL SYSTEM & CONN TISSUE W/O MCC", "Charge": "4681.2", "Category": "Standard"}, {"Description": " TENDONITIS, MYOSITIS & BURSITIS W/O MCC", "Charge": "5233.55", "Category": "Standard"}, {"Description": " FX, SPRN, STRN & DISL EXCEPT FEMUR, HIP, PELVIS & THIGH W/O MCC", "Charge": "4860.52", "Category": "Standard"}, {"Description": " CELLULITIS W MCC", "Charge": "9204.77", "Category": "Standard"}, {"Description": " SIGNS & SYMPTOMS W/O MCC", "Charge": "4921.36", "Category": "Standard"}, {"Description": " MAJOR HIP AND KNEE JOINT REPLACEMENT OR REATTACHMENT OF LOWER EXTREM", "Charge": "20448.67", "Category": "Standard"}, {"Description": " CARDIAC ARRHYTHMIA & CONDUCTION DISORDERS W MCC", "Charge": "8225.2", "Category": "Standard"}, {"Description": "Level 5 Urology and Related Services", "Charge": "3278.45", "Category": "DRG"}, {"Description": "Level 2 Pacemaker and Similar Procedures", "Charge": "6985.19", "Category": "DRG"}, {"Description": "Level 3 Pacemaker and Similar Procedures", "Charge": "9552.86", "Category": "DRG"}, {"Description": "Level 3 Upper GI Procedures", "Charge": "2307.89", "Category": "DRG"}, {"Description": "Level 3 Lower GI Procedures", "Charge": "2050.71", "Category": "DRG"}, {"Description": "Complex GI Procedures", "Charge": "3605.6", "Category": "DRG"}, {"Description": "Abdominal/Peritoneal/Biliary and Related Procedures", "Charge": "2649.83", "Category": "DRG"}, {"Description": "Level 4 Endovascular Procedures", "Charge": "14830.86", "Category": "DRG"}, {"Description": "Level 1 Laparoscopy and Related Services", "Charge": "3984.45", "Category": "DRG"}, {"Description": "Level 3 Urology and Related Services", "Charge": "1512.0", "Category": "DRG"}, {"Description": "Level 4 Urology and Related Services", "Charge": "2378.4", "Category": "DRG"}, {"Description": "Level 4 Gynecologic Procedures", "Charge": "1908.44", "Category": "DRG"}, {"Description": "Level 5 Gynecologic Procedures", "Charge": "3449.2", "Category": "DRG"}, {"Description": "Level 1 Nerve Procedures", "Charge": "1479.23", "Category": "DRG"}, {"Description": "Level 3 Neurostimulator and Related Procedures", "Charge": "19826.8", "Category": "DRG"}, {"Description": "Level 2 Laparoscopy and Related Services", "Charge": "6880.11", "Category": "DRG"}, {"Description": "Level 3 Endovascular Procedures", "Charge": "9461.78", "Category": "DRG"}, {"Description": "Level 2 Upper GI Procedures", "Charge": "1244.54", "Category": "DRG"}, {"Description": "Level 1 Endovascular Procedures", "Charge": "2310.69", "Category": "DRG"}, {"Description": "Comprehensive Observation Services", "Charge": "2108.54", "Category": "DRG"}, {"Description": "Level 2 Excision/ Biopsy/ Incision and Drainage", "Charge": "1149.64", "Category": "DRG"}, {"Description": "Level 2 Endovascular Procedures", "Charge": "4370.4", "Category": "DRG"}, {"Description": "Level 3 Excision/ Biopsy/ Incision and Drainage", "Charge": "1935.11", "Category": "DRG"}, {"Description": "Level 1 Breast/Lymphatic Surgery and Related Procedures", "Charge": "2313.21", "Category": "DRG"}, {"Description": "Level 2 Breast/Lymphatic Surgery and Related Procedures", "Charge": "4193.51", "Category": "DRG"}, {"Description": "Level 3 Musculoskeletal Procedures", "Charge": "2266.69", "Category": "DRG"}, {"Description": "Level 2 Musculoskeletal Procedures", "Charge": "1116.71", "Category": "DRG"}, {"Description": "Level 5 Musculoskeletal Procedures", "Charge": "10050.84", "Category": "DRG"}, {"Description": "Level 4 Airway Endoscopy", "Charge": "2306.94", "Category": "DRG"}, {"Description": "Level 5 ENT Procedures", "Charge": "3918.88", "Category": "DRG"}, {"Description": "Level 4 Musculoskeletal Procedures", "Charge": "4886.14", "Category": "DRG"}]