[{"Description":"G.I. OBSTRUCTION W MCC","Charge":"9242.07","Category":"Standard"},{"Description":"OTHER RESP SYSTEM O.R. PROCEDURES W MCC","Charge":"21755.8","Category":"Standard"},{"Description":"CRANIOTOMY W MAJOR DEVICE IMPLANT OR ACUTE CNS PDX W MCC OR CHEMOTHE","Charge":"33008.84","Category":"Standard"},{"Description":"PERITONEAL ADHESIOLYSIS W/O CC/MCC","Charge":"8799.86","Category":"Standard"},{"Description":"HERNIA PROCEDURES EXCEPT INGUINAL & FEMORAL W CC","Charge":"9574.06","Category":"Standard"},{"Description":"HERNIA PROCEDURES EXCEPT INGUINAL & FEMORAL W/O CC/MCC","Charge":"8126.43","Category":"Standard"},{"Description":"OTHER DIGESTIVE SYSTEM O.R. PROCEDURES W MCC","Charge":"24794.54","Category":"Standard"},{"Description":"OTHER DIGESTIVE SYSTEM O.R. PROCEDURES W CC","Charge":"13690.64","Category":"Standard"},{"Description":"MAJOR CHEST PROCEDURES W/O CC/MCC","Charge":"11337.82","Category":"Standard"},{"Description":"G.I. OBSTRUCTION W CC","Charge":"5748.47","Category":"Standard"},{"Description":"AUTOLOGOUS BONE MARROW TRANSPLANT W CC/MCC","Charge":"39093.5","Category":"Standard"},{"Description":" ECMO OR TRACH W MV >96 HRS OR PDX EXC FACE, MOUTH & NECK W MAJ O.R.","Charge":"109085.63","Category":"Standard"},{"Description":" ESOPHAGITIS, GASTROENT & MISC DIGEST DISORDERS W MCC","Charge":"7574.64","Category":"Standard"},{"Description":"G.I. OBSTRUCTION W/O CC/MCC","Charge":"3899.43","Category":"Standard"},{"Description":"MAJOR GASTROINTESTINAL DISORDERS & PERITONEAL INFECTIONS W CC","Charge":"6039.53","Category":"Standard"},{"Description":"DIGESTIVE MALIGNANCY W CC","Charge":"8209.09","Category":"Standard"},{"Description":"G.I. HEMORRHAGE W MCC","Charge":"12099.59","Category":"Standard"},{"Description":"OTHER RESP SYSTEM O.R. PROCEDURES W CC","Charge":"12105.9","Category":"Standard"},{"Description":"G.I. HEMORRHAGE W CC","Charge":"6412.36","Category":"Standard"},{"Description":"G.I. HEMORRHAGE W/O CC/MCC","Charge":"4396.69","Category":"Standard"},{"Description":" TRACH W MV >96 HRS OR PDX EXC FACE, MOUTH & NECK W/O MAJ O.R.","Charge":"69627.32","Category":"Standard"},{"Description":"PULMONARY EMBOLISM W MCC","Charge":"9435.79","Category":"Standard"},{"Description":"RENAL FAILURE W/O CC/MCC","Charge":"3883.5","Category":"Standard"},{"Description":"DISORDERS OF THE BILIARY TRACT W MCC","Charge":"11987.83","Category":"Standard"},{"Description":"PERMANENT CARDIAC PACEMAKER IMPLANT W/O CC/MCC","Charge":"13393.7","Category":"Standard"},{"Description":"PERMANENT CARDIAC PACEMAKER IMPLANT W CC","Charge":"16422.47","Category":"Standard"},{"Description":"PERMANENT CARDIAC PACEMAKER IMPLANT W MCC","Charge":"23436.21","Category":"Standard"},{"Description":"CORONARY BYPASS W/O CARDIAC CATH W/O MCC","Charge":"24659.36","Category":"Standard"},{"Description":"CORONARY BYPASS W/O CARDIAC CATH W MCC","Charge":"34913.28","Category":"Standard"},{"Description":"CORONARY BYPASS W CARDIAC CATH W/O MCC","Charge":"31430.52","Category":"Standard"},{"Description":"CORONARY BYPASS W CARDIAC CATH W MCC","Charge":"44300.21","Category":"Standard"},{"Description":"CARDIAC VALVE & OTH MAJ CARDIOTHORACIC PROC W/O CARD CATH W CC","Charge":"33490.22","Category":"Standard"},{"Description":"CARDIAC VALVE & OTH MAJ CARDIOTHORACIC PROC W/O CARD CATH W MCC","Charge":"51650.24","Category":"Standard"},{"Description":"CARDIAC VALVE & OTH MAJ CARDIOTHORACIC PROC W CARD CATH W MCC","Charge":"68291.94","Category":"Standard"},{"Description":"OTHER HEART ASSIST SYSTEM IMPLANT","Charge":"97752.67","Category":"Standard"},{"Description":"RESPIRATORY SYSTEM DIAGNOSIS W VENTILATOR SUPPORT <=96 HOURS","Charge":"14611.74","Category":"Standard"},{"Description":"RESPIRATORY SYSTEM DIAGNOSIS W VENTILATOR SUPPORT >96 HOURS","Charge":"28172.86","Category":"Standard"},{"Description":"BRONCHITIS & ASTHMA W CC/MCC","Charge":"4837.64","Category":"Standard"},{"Description":"PNEUMOTHORAX W CC","Charge":"6040.75","Category":"Standard"},{"Description":"INTERSTITIAL LUNG DISEASE W MCC","Charge":"10317.73","Category":"Standard"},{"Description":"SIMPLE PNEUMONIA & PLEURISY W CC","Charge":"6001.91","Category":"Standard"},{"Description":"SIMPLE PNEUMONIA & PLEURISY W MCC","Charge":"8409.18","Category":"Standard"},{"Description":"CHRONIC OBSTRUCTIVE PULMONARY DISEASE W CC","Charge":"5961.09","Category":"Standard"},{"Description":"CHRONIC OBSTRUCTIVE PULMONARY DISEASE W MCC","Charge":"7076.93","Category":"Standard"},{"Description":"PULMONARY EDEMA & RESPIRATORY FAILURE","Charge":"8225.3","Category":"Standard"},{"Description":"MAJOR CHEST TRAUMA W CC","Charge":"5970.83","Category":"Standard"},{"Description":"MAJOR CHEST TRAUMA W MCC","Charge":"9851.77","Category":"Standard"},{"Description":"RESPIRATORY NEOPLASMS W CC","Charge":"7572.25","Category":"Standard"},{"Description":"RESPIRATORY NEOPLASMS W MCC","Charge":"11202.39","Category":"Standard"},{"Description":"RESPIRATORY INFECTIONS & INFLAMMATIONS W MCC","Charge":"11800.74","Category":"Standard"},{"Description":"MAJOR CHEST PROCEDURES W CC","Charge":"15913.39","Category":"Standard"},{"Description":"PULMONARY EMBOLISM W/O MCC","Charge":"6121.42","Category":"Standard"},{"Description":"DISORDERS OF THE BILIARY TRACT W CC","Charge":"6768.1","Category":"Standard"},{"Description":" DISORDERS OF LIVER EXCEPT MALIG,CIRR,ALC HEPA W CC","Charge":"6206.09","Category":"Standard"},{"Description":"MAJOR CHEST PROCEDURES W MCC","Charge":"43245.19","Category":"Standard"},{"Description":"Level 4 Airway Endoscopy","Charge":"1752.16","Category":"DRG"},{"Description":"Level 1 Endovascular Procedures","Charge":"1766.19","Category":"DRG"},{"Description":"HEART FAILURE & SHOCK W CC","Charge":"6030.9","Category":"Standard"},{"Description":"HEART FAILURE & SHOCK W/O CC/MCC","Charge":"4281.14","Category":"Standard"},{"Description":"PERIPHERAL VASCULAR DISORDERS W CC","Charge":"6014.31","Category":"Standard"},{"Description":"HYPERTENSION W MCC","Charge":"7198.75","Category":"Standard"},{"Description":"HYPERTENSION W/O MCC","Charge":"4233.17","Category":"Standard"},{"Description":"CARDIAC ARRHYTHMIA & CONDUCTION DISORDERS W MCC","Charge":"8166.15","Category":"Standard"},{"Description":"CARDIAC ARRHYTHMIA & CONDUCTION DISORDERS W CC","Charge":"5079.66","Category":"Standard"},{"Description":"CARDIAC ARRHYTHMIA & CONDUCTION DISORDERS W/O CC/MCC","Charge":"3455.1","Category":"Standard"},{"Description":"SYNCOPE & COLLAPSE","Charge":"5041.56","Category":"Standard"},{"Description":"CHEST PAIN","Charge":"4587.9","Category":"Standard"},{"Description":"OTHER CIRCULATORY SYSTEM DIAGNOSES W MCC","Charge":"12692.07","Category":"Standard"},{"Description":"NONSPECIFIC CEREBROVASCULAR DISORDERS W MCC","Charge":"10311.11","Category":"Standard"},{"Description":"NONSPECIFIC CEREBROVASCULAR DISORDERS W CC","Charge":"6466.86","Category":"Standard"},{"Description":"TRANSIENT ISCHEMIA","Charge":"4864.13","Category":"Standard"},{"Description":" TRAUMATIC STUPOR & COMA, COMA >1 HR W MCC","Charge":"13155.42","Category":"Standard"},{"Description":" TRAUMATIC STUPOR & COMA, COMA <1 HR W CC","Charge":"7455.03","Category":"Standard"},{"Description":" TRAUMATIC STUPOR & COMA, COMA <1 HR W/O CC/MCC","Charge":"5385.24","Category":"Standard"},{"Description":"OTHER DISORDERS OF NERVOUS SYSTEM W MCC","Charge":"10233.18","Category":"Standard"},{"Description":"OTHER DISORDERS OF NERVOUS SYSTEM W CC","Charge":"6048.88","Category":"Standard"},{"Description":"DISORDERS OF PANCREAS EXCEPT MALIGNANCY W/O CC/MCC","Charge":"4377.44","Category":"Standard"},{"Description":"DISORDERS OF PANCREAS EXCEPT MALIGNANCY W CC","Charge":"5674.4","Category":"Standard"},{"Description":"DISORDERS OF PANCREAS EXCEPT MALIGNANCY W MCC","Charge":"9756.53","Category":"Standard"},{"Description":"LAPAROSCOPIC CHOLECYSTECTOMY W/O C.D.E. W/O CC/MCC","Charge":"6760.45","Category":"Standard"},{"Description":"LAPAROSCOPIC CHOLECYSTECTOMY W/O C.D.E. W CC","Charge":"10562.43","Category":"Standard"},{"Description":"OTHER DISORDERS OF NERVOUS SYSTEM W/O CC/MCC","Charge":"4743.31","Category":"Standard"},{"Description":"SEIZURES W MCC","Charge":"12582.67","Category":"Standard"},{"Description":"SEIZURES W/O MCC","Charge":"4814.85","Category":"Standard"},{"Description":"HEADACHES W/O MCC","Charge":"4860.31","Category":"Standard"},{"Description":" TRAUMATIC STUPOR & COMA, COMA <1 HR W MCC","Charge":"11857.0","Category":"Standard"},{"Description":"Level 2 Endovascular Procedures","Charge":"3470.17","Category":"DRG"},{"Description":"INTRACRANIAL HEMORRHAGE OR CEREBRAL INFARCTION W/O CC/MCC","Charge":"4376.36","Category":"Standard"},{"Description":"Level 3 Excision/ Biopsy/ Incision and Drainage","Charge":"1547.06","Category":"DRG"},{"Description":"Level 5 ENT Procedures","Charge":"3018.81","Category":"DRG"},{"Description":"Level 4 ENT Procedures","Charge":"1629.22","Category":"DRG"},{"Description":"PERC CARDIOVASC PROC W DRUG","Charge":"19850.06","Category":"Standard"},{"Description":"Level 3 Airway Endoscopy","Charge":"937.31","Category":"DRG"},{"Description":"Level 4 Musculoskeletal Procedures","Charge":"3896.68","Category":"DRG"},{"Description":"Level 5 Gynecologic Procedures","Charge":"2724.53","Category":"DRG"},{"Description":"Level 6 Gynecologic Procedures","Charge":"4157.33","Category":"DRG"},{"Description":"Level 1 Nerve Procedures","Charge":"1143.69","Category":"DRG"},{"Description":"Level 2 Nerve Procedures","Charge":"3111.89","Category":"DRG"},{"Description":"Level 2 Neurostimulator and Related Procedures","Charge":"4036.94","Category":"DRG"},{"Description":"Level 3 Neurostimulator and Related Procedures","Charge":"14995.68","Category":"DRG"},{"Description":"Level 4 Neurostimulator and Related Procedures","Charge":"23491.43","Category":"DRG"},{"Description":"Level 1 Intraocular Procedures","Charge":"1342.42","Category":"DRG"},{"Description":"Level 2 Excision/ Biopsy/ Incision and Drainage","Charge":"887.6","Category":"DRG"},{"Description":"Level 2 Intraocular Procedures","Charge":"2413.44","Category":"DRG"},{"Description":"Level 4 Extraocular, Repair, and Plastic Eye Procedures","Charge":"2036.46","Category":"DRG"},{"Description":"Level 7 Radiation Therapy","Charge":"5221.19","Category":"DRG"},{"Description":"Comprehensive Observation Services","Charge":"1637.39","Category":"DRG"},{"Description":"PERITONEAL ADHESIOLYSIS W CC","Charge":"14975.73","Category":"Standard"},{"Description":"MAJOR SMALL & LARGE BOWEL PROCEDURES W/O CC/MCC","Charge":"10025.36","Category":"Standard"},{"Description":"MAJOR SMALL & LARGE BOWEL PROCEDURES W CC","Charge":"14874.47","Category":"Standard"},{"Description":"MAJOR SMALL & LARGE BOWEL PROCEDURES W MCC","Charge":"31709.63","Category":"Standard"},{"Description":"Level 3 Musculoskeletal Procedures","Charge":"1746.11","Category":"DRG"},{"Description":"Level 2 Musculoskeletal Procedures","Charge":"890.01","Category":"DRG"},{"Description":" STOMACH, ESOPHAGEAL & DUODENAL PROC W/O CC/MCC","Charge":"9136.46","Category":"Standard"},{"Description":" STOMACH, ESOPHAGEAL & DUODENAL PROC W MCC","Charge":"30383.4","Category":"Standard"},{"Description":"Level 2 Breast/Lymphatic Surgery and Related Procedures","Charge":"3312.46","Category":"DRG"},{"Description":"Level 1 Breast/Lymphatic Surgery and Related Procedures","Charge":"1830.83","Category":"DRG"},{"Description":"Level 3 Extraocular, Repair, and Plastic Eye Procedures","Charge":"1263.77","Category":"DRG"},{"Description":"Level 3 Endovascular Procedures","Charge":"7584.96","Category":"DRG"},{"Description":"OTHER VASCULAR PROCEDURES W MCC","Charge":"21451.21","Category":"Standard"},{"Description":"Level 2 Electrophysiologic Procedures","Charge":"3750.96","Category":"DRG"},{"Description":"CELLULITIS W MCC","Charge":"9454.1","Category":"Standard"},{"Description":" OTHER SKIN, SUBCUT TISS & BREAST PROC W MCC","Charge":"15703.45","Category":"Standard"},{"Description":" FX, SPRN, STRN & DISL EXCEPT FEMUR, HIP, PELVIS & THIGH W/O MCC","Charge":"4960.0","Category":"Standard"},{"Description":"INFECTIOUS & PARASITIC DISEASES W O.R. PROCEDURE W MCC","Charge":"35344.85","Category":"Standard"},{"Description":"INFECTIOUS & PARASITIC DISEASES W O.R. PROCEDURE W CC","Charge":"15408.36","Category":"Standard"},{"Description":"POSTOPERATIVE OR POST","Charge":"13573.12","Category":"Standard"},{"Description":"SEPTICEMIA OR SEVERE SEPSIS W MV >96 HOURS","Charge":"36102.42","Category":"Standard"},{"Description":"SEPTICEMIA OR SEVERE SEPSIS W/O MV >96 HOURS W MCC","Charge":"11314.86","Category":"Standard"},{"Description":"EXTRACRANIAL PROCEDURES W/O CC/MCC","Charge":"6539.94","Category":"Standard"},{"Description":"EXTRACRANIAL PROCEDURES W CC","Charge":"10241.0","Category":"Standard"},{"Description":"SEPTICEMIA OR SEVERE SEPSIS W/O MV >96 HOURS W/O MCC","Charge":"6425.51","Category":"Standard"},{"Description":"ORGANIC DISTURBANCES & INTELLECTUAL DISABILITY","Charge":"7673.73","Category":"Standard"},{"Description":"CELLULITIS W/O MCC","Charge":"5416.28","Category":"Standard"},{"Description":"OTHER O.R. PROCEDURES FOR INJURIES W CC","Charge":"12995.47","Category":"Standard"},{"Description":"POISONING & TOXIC EFFECTS OF DRUGS W/O MCC","Charge":"4822.0","Category":"Standard"},{"Description":"COMPLICATIONS OF TREATMENT W MCC","Charge":"11683.74","Category":"Standard"},{"Description":"COMPLICATIONS OF TREATMENT W CC","Charge":"6462.14","Category":"Standard"},{"Description":"SIGNS & SYMPTOMS W/O MCC","Charge":"4937.31","Category":"Standard"},{"Description":"EXTENSIVE O.R. PROCEDURE UNRELATED TO PRINCIPAL DIAGNOSIS W MCC","Charge":"31965.82","Category":"Standard"},{"Description":"EXTENSIVE O.R. PROCEDURE UNRELATED TO PRINCIPAL DIAGNOSIS W CC","Charge":"17334.6","Category":"Standard"},{"Description":"LAPAROSCOPIC CHOLECYSTECTOMY W/O C.D.E. W MCC","Charge":"15850.58","Category":"Standard"},{"Description":" PANCREAS, LIVER & SHUNT PROCEDURES W CC","Charge":"16577.93","Category":"Standard"},{"Description":"MEDICAL BACK PROBLEMS W/O MCC","Charge":"5762.88","Category":"Standard"},{"Description":"MEDICAL BACK PROBLEMS W MCC","Charge":"9815.17","Category":"Standard"},{"Description":"OTHER DIGESTIVE SYSTEM DIAGNOSES W/O CC/MCC","Charge":"4585.55","Category":"Standard"},{"Description":"OTHER DIGESTIVE SYSTEM DIAGNOSES W CC","Charge":"6502.63","Category":"Standard"},{"Description":"POISONING & TOXIC EFFECTS OF DRUGS W MCC","Charge":"9280.26","Category":"Standard"},{"Description":"CHEMOTHERAPY W/O ACUTE LEUKEMIA AS SECONDARY DIAGNOSIS W CC","Charge":"8876.45","Category":"Standard"},{"Description":"LYMPHOMA & NON","Charge":"20081.61","Category":"Standard"},{"Description":"CHEMO W ACUTE LEUKEMIA AS SDX W/O CC/MCC","Charge":"8080.0","Category":"Standard"},{"Description":"RENAL FAILURE W CC","Charge":"6046.23","Category":"Standard"},{"Description":"RENAL FAILURE W MCC","Charge":"9257.46","Category":"Standard"},{"Description":"OTHER KIDNEY & URINARY TRACT PROCEDURES W MCC","Charge":"23986.73","Category":"Standard"},{"Description":"ENDOCRINE DISORDERS W MCC","Charge":"10366.94","Category":"Standard"},{"Description":" MISC DISORDERS OF NUTRITION,METABOLISM,FLUIDS/ELECTROLYTES W/O MCC","Charge":"4712.51","Category":"Standard"},{"Description":" MISC DISORDERS OF NUTRITION,METABOLISM,FLUIDS/ELECTROLYTES W MCC","Charge":"7582.27","Category":"Standard"},{"Description":"DIABETES W CC","Charge":"5588.64","Category":"Standard"},{"Description":"DIABETES W MCC","Charge":"8771.36","Category":"Standard"},{"Description":"KIDNEY & URINARY TRACT INFECTIONS W/O MCC","Charge":"5222.65","Category":"Standard"},{"Description":"URINARY STONES W/O ESW LITHOTRIPSY W/O MCC","Charge":"4783.14","Category":"Standard"},{"Description":"OTHER KIDNEY & URINARY TRACT DIAGNOSES W MCC","Charge":"10178.44","Category":"Standard"},{"Description":" AMPUTAT OF LOWER LIMB FOR ENDOCRINE,NUTRIT,& METABOL DIS W CC","Charge":"11658.52","Category":"Standard"},{"Description":"OTHER KIDNEY & URINARY TRACT DIAGNOSES W CC","Charge":"6261.07","Category":"Standard"},{"Description":" TRAUMA TO THE SKIN, SUBCUT TISS & BREAST W/O MCC","Charge":"5635.82","Category":"Standard"},{"Description":"MAJOR MALE PELVIC PROCEDURES W CC/MCC","Charge":"9376.45","Category":"Standard"},{"Description":"MAJOR MALE PELVIC PROCEDURES W/O CC/MCC","Charge":"7753.21","Category":"Standard"},{"Description":"MAJOR HEMATOL/IMMUN DIAG EXC SICKLE CELL CRISIS & COAGUL W CC","Charge":"7719.0","Category":"Standard"},{"Description":"RED BLOOD CELL DISORDERS W MCC","Charge":"8725.81","Category":"Standard"},{"Description":"RED BLOOD CELL DISORDERS W/O MCC","Charge":"6039.39","Category":"Standard"},{"Description":"COAGULATION DISORDERS","Charge":"52144.33","Category":"Standard"},{"Description":"INTRACRANIAL HEMORRHAGE OR CEREBRAL INFARCTION W CC OR TPA IN 24 HRS","Charge":"6731.21","Category":"Standard"},{"Description":"INTRACRANIAL HEMORRHAGE OR CEREBRAL INFARCTION W MCC","Charge":"11321.05","Category":"Standard"},{"Description":" ISCHEMIC STROKE, PRECEREBRAL OCCLUSION OR TRANSIENT ISCHEMIA W THROM","Charge":"11822.53","Category":"Standard"},{"Description":"ACUTE ISCHEMIC STROKE W USE OF THROMBOLYTIC AGENT W MCC","Charge":"18187.19","Category":"Standard"},{"Description":"DEGENERATIVE NERVOUS SYSTEM DISORDERS W/O MCC","Charge":"7132.06","Category":"Standard"},{"Description":"DEGENERATIVE NERVOUS SYSTEM DISORDERS W MCC","Charge":"11673.33","Category":"Standard"},{"Description":"NERVOUS SYSTEM NEOPLASMS W MCC","Charge":"8248.09","Category":"Standard"},{"Description":"OTHER DIGESTIVE SYSTEM DIAGNOSES W MCC","Charge":"10589.75","Category":"Standard"},{"Description":"Level 4 Endovascular Procedures","Charge":"11757.18","Category":"DRG"},{"Description":" ESOPHAGITIS, GASTROENT & MISC DIGEST DISORDERS W/O MCC","Charge":"4863.16","Category":"Standard"},{"Description":"Level 2 Upper GI Procedures","Charge":"958.84","Category":"DRG"},{"Description":" CIRCULATORY DISORDERS EXCEPT AMI, W CARD CATH W/O MCC","Charge":"6881.24","Category":"Standard"},{"Description":" CIRCULATORY DISORDERS EXCEPT AMI, W CARD CATH W MCC","Charge":"14286.84","Category":"Standard"},{"Description":" ACUTE MYOCARDIAL INFARCTION, DISCHARGED ALIVE W/O CC/MCC","Charge":"4709.29","Category":"Standard"},{"Description":" ACUTE MYOCARDIAL INFARCTION, DISCHARGED ALIVE W CC","Charge":"6531.43","Category":"Standard"},{"Description":" ACUTE MYOCARDIAL INFARCTION, DISCHARGED ALIVE W MCC","Charge":"9935.41","Category":"Standard"},{"Description":"PERCUTANEOUS INTRACARDIAC PROCEDURES W/O MCC","Charge":"16183.48","Category":"Standard"},{"Description":"PERCUTANEOUS INTRACARDIAC PROCEDURES W MCC","Charge":"23518.25","Category":"Standard"},{"Description":"OTHER MAJOR CARDIOVASCULAR PROCEDURES W/O CC/MCC","Charge":"14494.69","Category":"Standard"},{"Description":"OTHER MAJOR CARDIOVASCULAR PROCEDURES W CC","Charge":"21748.15","Category":"Standard"},{"Description":"OTHER MAJOR CARDIOVASCULAR PROCEDURES W MCC","Charge":"30905.32","Category":"Standard"},{"Description":"AORTIC AND HEART ASSIST PROCEDURES EXCEPT PULSATION BALLOON W/O MCC","Charge":"24604.35","Category":"Standard"},{"Description":"Level 3 Pacemaker and Similar Procedures","Charge":"7481.7","Category":"DRG"},{"Description":"HEART FAILURE & SHOCK W MCC","Charge":"9467.59","Category":"Standard"},{"Description":"ENDOVASCULAR CARDIAC VALVE REPLACEMENT W/O MCC","Charge":"41275.11","Category":"Standard"},{"Description":"CRANIOTOMY & ENDOVASCULAR INTRACRANIAL PROCEDURES W CC","Charge":"20849.47","Category":"Standard"},{"Description":"CRANIOTOMY & ENDOVASCULAR INTRACRANIAL PROCEDURES W MCC","Charge":"27164.51","Category":"Standard"},{"Description":"ENDOVASCULAR CARDIAC VALVE REPLACEMENT W MCC","Charge":"54203.96","Category":"Standard"},{"Description":"OTHER VASCULAR PROCEDURES W/O CC/MCC","Charge":"10296.05","Category":"Standard"},{"Description":"OTHER VASCULAR PROCEDURES W CC","Charge":"15599.17","Category":"Standard"},{"Description":"KIDNEY & URINARY TRACT INFECTIONS W MCC","Charge":"6764.45","Category":"Standard"},{"Description":"PERC CARDIOVASC PROC W/O CORONARY ARTERY STENT W/O MCC","Charge":"10896.42","Category":"Standard"},{"Description":"PERC CARDIOVASC PROC W NON","Charge":"11871.05","Category":"Standard"},{"Description":"PERC CARDIOVASC PROC W NON","Charge":"20038.33","Category":"Standard"},{"Description":"PERC CARDIOVASC PROC W DRUG","Charge":"12838.11","Category":"Standard"},{"Description":"Level 2 Pacemaker and Similar Procedures","Charge":"5246.67","Category":"DRG"},{"Description":"Level 3 Electrophysiologic Procedures","Charge":"13980.48","Category":"DRG"},{"Description":"CRANIOTOMY & ENDOVASCULAR INTRACRANIAL PROCEDURES W/O CC/MCC","Charge":"14658.96","Category":"Standard"},{"Description":"OTHER CIRCULATORY SYSTEM DIAGNOSES W CC","Charge":"6120.33","Category":"Standard"},{"Description":"SPINAL FUSION EXCEPT CERVICAL W/O MCC","Charge":"24434.93","Category":"Standard"},{"Description":" WND DEBRID & SKN GRFT EXC HAND, FOR MUSCULO","Charge":"22943.75","Category":"Standard"},{"Description":"Level 2 ICD and Similar Procedures","Charge":"26199.39","Category":"DRG"},{"Description":"Level 1 ICD and Similar Procedures","Charge":"16875.22","Category":"DRG"},{"Description":"Level 4 Pacemaker and Similar Procedures","Charge":"14067.49","Category":"DRG"},{"Description":"Level 3 Lower GI Procedures","Charge":"1601.38","Category":"DRG"},{"Description":"Complex GI Procedures","Charge":"2875.82","Category":"DRG"},{"Description":"Abdominal/Peritoneal/Biliary and Related Procedures","Charge":"1941.44","Category":"DRG"},{"Description":"Level 1 Laparoscopy and Related Services","Charge":"3045.48","Category":"DRG"},{"Description":"Level 2 Laparoscopy and Related Services","Charge":"5240.36","Category":"DRG"},{"Description":"Level 3 Urology and Related Services","Charge":"1198.98","Category":"DRG"},{"Description":"Level 4 Urology and Related Services","Charge":"1866.36","Category":"DRG"},{"Description":"Level 5 Urology and Related Services","Charge":"2567.99","Category":"DRG"},{"Description":"Level 6 Urology and Related Services","Charge":"5692.71","Category":"DRG"},{"Description":"Level 7 Urology and Related Services","Charge":"12167.58","Category":"DRG"},{"Description":"Level 4 Gynecologic Procedures","Charge":"1510.1","Category":"DRG"},{"Description":"PATHOLOGICAL FRACTURES & MUSCULOSKELET & CONN TISS MALIG W CC","Charge":"7155.67","Category":"Standard"},{"Description":"PATHOLOGICAL FRACTURES & MUSCULOSKELET & CONN TISS MALIG W MCC","Charge":"10981.5","Category":"Standard"},{"Description":"BACK & NECK PROC EXC SPINAL FUSION W/O CC/MCC","Charge":"7796.62","Category":"Standard"},{"Description":"BACK & NECK PROC EXC SPINAL FUSION W CC","Charge":"10129.8","Category":"Standard"},{"Description":" LOWER EXTREM & HUMER PROC EXCEPT HIP,FOOT,FEMUR W/O CC/MCC","Charge":"10571.45","Category":"Standard"},{"Description":" LOWER EXTREM & HUMER PROC EXCEPT HIP,FOOT,FEMUR W CC","Charge":"13039.67","Category":"Standard"},{"Description":"HIP & FEMUR PROCEDURES EXCEPT MAJOR JOINT W/O CC/MCC","Charge":"10353.8","Category":"Standard"},{"Description":"HIP & FEMUR PROCEDURES EXCEPT MAJOR JOINT W CC","Charge":"12627.36","Category":"Standard"},{"Description":"HIP & FEMUR PROCEDURES EXCEPT MAJOR JOINT W MCC","Charge":"18911.48","Category":"Standard"},{"Description":"CERVICAL SPINAL FUSION W/O CC/MCC","Charge":"11321.85","Category":"Standard"},{"Description":"CERVICAL SPINAL FUSION W CC","Charge":"18269.08","Category":"Standard"},{"Description":"MAJOR JOINT REPLACEMENT OR REATTACHMENT OF LOWER EXTREMITY W/O MCC","Charge":"13421.38","Category":"Standard"},{"Description":"MAJOR HIP AND KNEE JOINT REPLACEMENT OR REATTACHMENT OF LOWER EXTREM","Charge":"18883.92","Category":"Standard"},{"Description":"Level 3 Upper GI Procedures","Charge":"1879.43","Category":"DRG"},{"Description":"Level 5 Musculoskeletal Procedures","Charge":"7668.24","Category":"DRG"}]