[{"Description":"G.I. HEMORRHAGE W MCC","Charge":"13091.69","Category":"Standard"},{"Description":"G.I. OBSTRUCTION W/O CC/MCC","Charge":"4567.23","Category":"Standard"},{"Description":"G.I. OBSTRUCTION W CC","Charge":"5901.05","Category":"Standard"},{"Description":"G.I. OBSTRUCTION W MCC","Charge":"10095.4","Category":"Standard"},{"Description":"INFLAMMATORY BOWEL DISEASE W/O CC/MCC","Charge":"4654.19","Category":"Standard"},{"Description":"INFLAMMATORY BOWEL DISEASE W CC","Charge":"6623.17","Category":"Standard"},{"Description":"COMPLICATED PEPTIC ULCER W CC","Charge":"7316.0","Category":"Standard"},{"Description":"PERITONEAL ADHESIOLYSIS W CC","Charge":"13997.88","Category":"Standard"},{"Description":"HERNIA PROCEDURES EXCEPT INGUINAL & FEMORAL W CC","Charge":"10482.04","Category":"Standard"},{"Description":"HERNIA PROCEDURES EXCEPT INGUINAL & FEMORAL W/O CC/MCC","Charge":"8348.44","Category":"Standard"},{"Description":"OTHER DIGESTIVE SYSTEM O.R. PROCEDURES W MCC","Charge":"24396.45","Category":"Standard"},{"Description":"G.I. HEMORRHAGE W/O CC/MCC","Charge":"4898.85","Category":"Standard"},{"Description":"MAJOR GASTROINTESTINAL DISORDERS & PERITONEAL INFECTIONS W CC","Charge":"8394.46","Category":"Standard"},{"Description":"DIGESTIVE MALIGNANCY W CC","Charge":"7677.25","Category":"Standard"},{"Description":"G.I. HEMORRHAGE W CC","Charge":"7012.32","Category":"Standard"},{"Description":"MAJOR GASTROINTESTINAL DISORDERS & PERITONEAL INFECTIONS W MCC","Charge":"12086.56","Category":"Standard"},{"Description":"PERIPHERAL VASCULAR DISORDERS W MCC","Charge":"13417.54","Category":"Standard"},{"Description":"CORONARY BYPASS W/O CARDIAC CATH W/O MCC","Charge":"25313.1","Category":"Standard"},{"Description":" ACUTE MYOCARDIAL INFARCTION, DISCHARGED ALIVE W CC","Charge":"6849.45","Category":"Standard"},{"Description":" ACUTE MYOCARDIAL INFARCTION, EXPIRED W MCC","Charge":"17552.23","Category":"Standard"},{"Description":" STOMACH, ESOPHAGEAL & DUODENAL PROC W/O CC/MCC","Charge":"10851.6","Category":"Standard"},{"Description":" STOMACH, ESOPHAGEAL & DUODENAL PROC W CC","Charge":"16981.84","Category":"Standard"},{"Description":" STOMACH, ESOPHAGEAL & DUODENAL PROC W MCC","Charge":"76926.88","Category":"Standard"},{"Description":"OTHER CIRCULATORY SYSTEM DIAGNOSES W CC","Charge":"6835.26","Category":"Standard"},{"Description":"OTHER CIRCULATORY SYSTEM DIAGNOSES W MCC","Charge":"17047.81","Category":"Standard"},{"Description":"CHEST PAIN","Charge":"4980.56","Category":"Standard"},{"Description":"SYNCOPE & COLLAPSE","Charge":"5637.13","Category":"Standard"},{"Description":"ANGINA PECTORIS","Charge":"4815.0","Category":"Standard"},{"Description":"CARDIAC ARRHYTHMIA & CONDUCTION DISORDERS W/O CC/MCC","Charge":"3991.32","Category":"Standard"},{"Description":"CARDIAC ARRHYTHMIA & CONDUCTION DISORDERS W CC","Charge":"5477.53","Category":"Standard"},{"Description":"CARDIAC ARRHYTHMIA & CONDUCTION DISORDERS W MCC","Charge":"8349.6","Category":"Standard"},{"Description":"HYPERTENSION W/O MCC","Charge":"4876.58","Category":"Standard"},{"Description":"HYPERTENSION W MCC","Charge":"7659.84","Category":"Standard"},{"Description":"ATHEROSCLEROSIS W/O MCC","Charge":"5032.12","Category":"Standard"},{"Description":"ATHEROSCLEROSIS W MCC","Charge":"7623.19","Category":"Standard"},{"Description":"PERIPHERAL VASCULAR DISORDERS W/O CC/MCC","Charge":"5609.68","Category":"Standard"},{"Description":" CIRCULATORY DISORDERS EXCEPT AMI, W CARD CATH W MCC","Charge":"17671.56","Category":"Standard"},{"Description":" CIRCULATORY DISORDERS EXCEPT AMI, W CARD CATH W/O MCC","Charge":"8321.54","Category":"Standard"},{"Description":"HEART FAILURE & SHOCK W MCC","Charge":"11016.49","Category":"Standard"},{"Description":"HEART FAILURE & SHOCK W CC","Charge":"6680.74","Category":"Standard"},{"Description":"HEART FAILURE & SHOCK W/O CC/MCC","Charge":"4989.48","Category":"Standard"},{"Description":" ACUTE MYOCARDIAL INFARCTION, DISCHARGED ALIVE W MCC","Charge":"12437.39","Category":"Standard"},{"Description":"CORONARY BYPASS W/O CARDIAC CATH W MCC","Charge":"31653.54","Category":"Standard"},{"Description":"PERCUTANEOUS INTRACARDIAC PROCEDURES W/O MCC","Charge":"16595.81","Category":"Standard"},{"Description":"OTHER MAJOR CARDIOVASCULAR PROCEDURES W CC","Charge":"22273.94","Category":"Standard"},{"Description":"AMPUTATION FOR CIRC SYS DISORDERS EXC UPPER LIMB & TOE W MCC","Charge":"28692.64","Category":"Standard"},{"Description":"AMPUTATION FOR CIRC SYS DISORDERS EXC UPPER LIMB & TOE W CC","Charge":"16012.27","Category":"Standard"},{"Description":"PERMANENT CARDIAC PACEMAKER IMPLANT W MCC","Charge":"28674.25","Category":"Standard"},{"Description":"PERIPHERAL VASCULAR DISORDERS W CC","Charge":"7450.28","Category":"Standard"},{"Description":"PERMANENT CARDIAC PACEMAKER IMPLANT W/O CC/MCC","Charge":"15335.11","Category":"Standard"},{"Description":"AICD GENERATOR PROCEDURES","Charge":"30490.53","Category":"Standard"},{"Description":"PERC CARDIOVASC PROC W DRUG","Charge":"22420.0","Category":"Standard"},{"Description":"PERC CARDIOVASC PROC W DRUG","Charge":"14627.08","Category":"Standard"},{"Description":"PERC CARDIOVASC PROC W NON","Charge":"21972.08","Category":"Standard"},{"Description":"PERC CARDIOVASC PROC W/O CORONARY ARTERY STENT W/O MCC","Charge":"11438.35","Category":"Standard"},{"Description":"OTHER VASCULAR PROCEDURES W MCC","Charge":"24078.2","Category":"Standard"},{"Description":"OTHER VASCULAR PROCEDURES W CC","Charge":"18925.54","Category":"Standard"},{"Description":"MAJOR SMALL & LARGE BOWEL PROCEDURES W/O CC/MCC","Charge":"9619.36","Category":"Standard"},{"Description":"MAJOR SMALL & LARGE BOWEL PROCEDURES W CC","Charge":"18884.04","Category":"Standard"},{"Description":"MAJOR SMALL & LARGE BOWEL PROCEDURES W MCC","Charge":"37420.75","Category":"Standard"},{"Description":"OTHER VASCULAR PROCEDURES W/O CC/MCC","Charge":"11385.18","Category":"Standard"},{"Description":"CARDIAC PACEMAKER REVISION EXCEPT DEVICE REPLACEMENT W MCC","Charge":"22882.83","Category":"Standard"},{"Description":"CARDIAC PACEMAKER REVISION EXCEPT DEVICE REPLACEMENT W CC","Charge":"14109.07","Category":"Standard"},{"Description":"OTHER CIRCULATORY SYSTEM O.R. PROCEDURES","Charge":"25550.23","Category":"Standard"},{"Description":"ENDOVASCULAR CARDIAC VALVE REPLACEMENT W MCC","Charge":"59319.5","Category":"Standard"},{"Description":"ENDOVASCULAR CARDIAC VALVE REPLACEMENT W/O MCC","Charge":"44616.25","Category":"Standard"},{"Description":"AORTIC AND HEART ASSIST PROCEDURES EXCEPT PULSATION BALLOON W/O MCC","Charge":"26975.44","Category":"Standard"},{"Description":"OTHER MAJOR CARDIOVASCULAR PROCEDURES W MCC","Charge":"31953.25","Category":"Standard"},{"Description":"PERCUTANEOUS INTRACARDIAC PROCEDURES W MCC","Charge":"24262.36","Category":"Standard"},{"Description":"PERMANENT CARDIAC PACEMAKER IMPLANT W CC","Charge":"17677.42","Category":"Standard"},{"Description":"INTRACRANIAL HEMORRHAGE OR CEREBRAL INFARCTION W MCC","Charge":"16988.0","Category":"Standard"},{"Description":"CORONARY BYPASS W CARDIAC CATH W MCC","Charge":"43588.19","Category":"Standard"},{"Description":"Level 2 Upper GI Procedures","Charge":"971.38","Category":"DRG"},{"Description":"Level 3 Upper GI Procedures","Charge":"1875.39","Category":"DRG"},{"Description":"HEART TRANSPLANT OR IMPLANT OF HEART ASSIST SYSTEM W MCC","Charge":"237641.31","Category":"Standard"},{"Description":" TRACH W MV >96 HRS OR PDX EXC FACE, MOUTH & NECK W/O MAJ O.R.","Charge":"72420.1","Category":"Standard"},{"Description":"LIVER TRANSPLANT W MCC OR INTESTINAL TRANSPLANT","Charge":"80332.65","Category":"Standard"},{"Description":"LUNG TRANSPLANT","Charge":"95771.27","Category":"Standard"},{"Description":"CRANIOTOMY W MAJOR DEVICE IMPLANT OR ACUTE CNS PDX W MCC OR CHEMOTHE","Charge":"34405.63","Category":"Standard"},{"Description":"CRANIOTOMY & ENDOVASCULAR INTRACRANIAL PROCEDURES W MCC","Charge":"29036.3","Category":"Standard"},{"Description":"CRANIOTOMY & ENDOVASCULAR INTRACRANIAL PROCEDURES W CC","Charge":"21820.32","Category":"Standard"},{"Description":"Level 2 ICD and Similar Procedures","Charge":"27436.84","Category":"DRG"},{"Description":"CRANIOTOMY & ENDOVASCULAR INTRACRANIAL PROCEDURES W/O CC/MCC","Charge":"13312.78","Category":"Standard"},{"Description":"SPINAL PROCEDURES W CC OR SPINAL NEUROSTIMULATORS","Charge":"22536.36","Category":"Standard"},{"Description":"CAROTID ARTERY STENT PROCEDURE W CC","Charge":"17182.85","Category":"Standard"},{"Description":"EXTRACRANIAL PROCEDURES W CC","Charge":"11591.42","Category":"Standard"},{"Description":"EXTRACRANIAL PROCEDURES W/O CC/MCC","Charge":"7447.81","Category":"Standard"},{"Description":"PERIPH/CRANIAL NERVE & OTHER NERV SYST PROC W MCC","Charge":"45275.76","Category":"Standard"},{"Description":"PERIPH/CRANIAL NERVE & OTHER NERV SYST PROC W CC OR PERIPH NEUROSTIM","Charge":"14354.43","Category":"Standard"},{"Description":"PERIPH/CRANIAL NERVE & OTHER NERV SYST PROC W/O CC/MCC","Charge":"11374.69","Category":"Standard"},{"Description":"DEGENERATIVE NERVOUS SYSTEM DISORDERS W MCC","Charge":"11661.29","Category":"Standard"},{"Description":"DEGENERATIVE NERVOUS SYSTEM DISORDERS W/O MCC","Charge":"7410.08","Category":"Standard"},{"Description":"SPINAL PROCEDURES W MCC","Charge":"38625.15","Category":"Standard"},{"Description":"Level 1 ICD and Similar Procedures","Charge":"18314.82","Category":"DRG"},{"Description":"Level 4 Pacemaker and Similar Procedures","Charge":"14664.67","Category":"DRG"},{"Description":"Level 3 Pacemaker and Similar Procedures","Charge":"7490.8","Category":"DRG"},{"Description":"Level 2 Excision/ Biopsy/ Incision and Drainage","Charge":"903.2","Category":"DRG"},{"Description":"Level 3 Excision/ Biopsy/ Incision and Drainage","Charge":"1525.88","Category":"DRG"},{"Description":"Level 1 Breast/Lymphatic Surgery and Related Procedures","Charge":"1641.68","Category":"DRG"},{"Description":"Level 2 Breast/Lymphatic Surgery and Related Procedures","Charge":"3364.23","Category":"DRG"},{"Description":"Level 2 Musculoskeletal Procedures","Charge":"898.49","Category":"DRG"},{"Description":"Level 3 Musculoskeletal Procedures","Charge":"1716.81","Category":"DRG"},{"Description":"Level 4 Musculoskeletal Procedures","Charge":"3777.59","Category":"DRG"},{"Description":"Level 5 Musculoskeletal Procedures","Charge":"7673.6","Category":"DRG"},{"Description":"Level 3 Airway Endoscopy","Charge":"935.01","Category":"DRG"},{"Description":"Level 4 Airway Endoscopy","Charge":"1803.6","Category":"DRG"},{"Description":"Level 5 Airway Endoscopy","Charge":"3236.88","Category":"DRG"},{"Description":"Level 4 ENT Procedures","Charge":"1577.73","Category":"DRG"},{"Description":"Level 5 ENT Procedures","Charge":"3034.16","Category":"DRG"},{"Description":"Cochlear Implant Procedure","Charge":"27817.35","Category":"DRG"},{"Description":"Level 1 Endovascular Procedures","Charge":"1797.69","Category":"DRG"},{"Description":"Level 2 Endovascular Procedures","Charge":"3583.65","Category":"DRG"},{"Description":"Level 3 Endovascular Procedures","Charge":"7784.94","Category":"DRG"},{"Description":"Level 4 Endovascular Procedures","Charge":"12430.83","Category":"DRG"},{"Description":"Level 2 Electrophysiologic Procedures","Charge":"3811.03","Category":"DRG"},{"Description":"Level 3 Electrophysiologic Procedures","Charge":"14078.68","Category":"DRG"},{"Description":"Level 2 Pacemaker and Similar Procedures","Charge":"5252.44","Category":"DRG"},{"Description":"MULTIPLE SCLEROSIS & CEREBELLAR ATAXIA W CC","Charge":"6778.42","Category":"Standard"},{"Description":" ESOPHAGITIS, GASTROENT & MISC DIGEST DISORDERS W MCC","Charge":"9921.89","Category":"Standard"},{"Description":"INTRACRANIAL HEMORRHAGE OR CEREBRAL INFARCTION W CC OR TPA IN 24 HRS","Charge":"7088.8","Category":"Standard"},{"Description":"INTRACRANIAL HEMORRHAGE OR CEREBRAL INFARCTION W/O CC/MCC","Charge":"4739.15","Category":"Standard"},{"Description":"PULMONARY EDEMA & RESPIRATORY FAILURE","Charge":"9215.37","Category":"Standard"},{"Description":"CHRONIC OBSTRUCTIVE PULMONARY DISEASE W MCC","Charge":"8104.47","Category":"Standard"},{"Description":"CHRONIC OBSTRUCTIVE PULMONARY DISEASE W CC","Charge":"6746.94","Category":"Standard"},{"Description":"CHRONIC OBSTRUCTIVE PULMONARY DISEASE W/O CC/MCC","Charge":"4679.08","Category":"Standard"},{"Description":"SIMPLE PNEUMONIA & PLEURISY W MCC","Charge":"10064.05","Category":"Standard"},{"Description":"SIMPLE PNEUMONIA & PLEURISY W CC","Charge":"6629.57","Category":"Standard"},{"Description":"INTERSTITIAL LUNG DISEASE W MCC","Charge":"10083.43","Category":"Standard"},{"Description":"PNEUMOTHORAX W CC","Charge":"7220.67","Category":"Standard"},{"Description":"BRONCHITIS & ASTHMA W CC/MCC","Charge":"6489.21","Category":"Standard"},{"Description":"RESPIRATORY SIGNS & SYMPTOMS","Charge":"5471.0","Category":"Standard"},{"Description":"OTHER RESPIRATORY SYSTEM DIAGNOSES W MCC","Charge":"9347.86","Category":"Standard"},{"Description":"OTHER RESPIRATORY SYSTEM DIAGNOSES W/O MCC","Charge":"7643.44","Category":"Standard"},{"Description":"RESPIRATORY SYSTEM DIAGNOSIS W VENTILATOR SUPPORT >96 HOURS","Charge":"40509.69","Category":"Standard"},{"Description":"RESPIRATORY SYSTEM DIAGNOSIS W VENTILATOR SUPPORT <=96 HOURS","Charge":"15760.4","Category":"Standard"},{"Description":"CARDIAC VALVE & OTH MAJ CARDIOTHORACIC PROC W CARD CATH W MCC","Charge":"74534.4","Category":"Standard"},{"Description":"CARDIAC VALVE & OTH MAJ CARDIOTHORACIC PROC W/O CARD CATH W MCC","Charge":"57823.93","Category":"Standard"},{"Description":"CARDIAC VALVE & OTH MAJ CARDIOTHORACIC PROC W/O CARD CATH W CC","Charge":"34839.38","Category":"Standard"},{"Description":"CARDIAC DEFIBRILLATOR IMPLANT W/O CARDIAC CATH W MCC","Charge":"44961.67","Category":"Standard"},{"Description":"CARDIAC DEFIBRILLATOR IMPLANT W/O CARDIAC CATH W/O MCC","Charge":"36153.07","Category":"Standard"},{"Description":"OTHER CARDIOTHORACIC PROCEDURES W MCC","Charge":"54230.11","Category":"Standard"},{"Description":"OTHER CARDIOTHORACIC PROCEDURES W/O MCC","Charge":"34311.12","Category":"Standard"},{"Description":"PLEURAL EFFUSION W CC","Charge":"7774.73","Category":"Standard"},{"Description":"CORONARY BYPASS W CARDIAC CATH W/O MCC","Charge":"30698.62","Category":"Standard"},{"Description":"PLEURAL EFFUSION W MCC","Charge":"9908.91","Category":"Standard"},{"Description":"RESPIRATORY INFECTIONS & INFLAMMATIONS W MCC","Charge":"12958.38","Category":"Standard"},{"Description":"TRANSIENT ISCHEMIA","Charge":"5139.75","Category":"Standard"},{"Description":"NONSPECIFIC CEREBROVASCULAR DISORDERS W MCC","Charge":"12105.89","Category":"Standard"},{"Description":"NONSPECIFIC CEREBROVASCULAR DISORDERS W CC","Charge":"7069.35","Category":"Standard"},{"Description":"NONSPECIFIC CEREBROVASCULAR DISORDERS W/O CC/MCC","Charge":"5290.38","Category":"Standard"},{"Description":"CRANIAL & PERIPHERAL NERVE DISORDERS W/O MCC","Charge":"6601.32","Category":"Standard"},{"Description":" TRAUMATIC STUPOR & COMA, COMA <1 HR W MCC","Charge":"13027.73","Category":"Standard"},{"Description":" TRAUMATIC STUPOR & COMA, COMA <1 HR W CC","Charge":"7087.62","Category":"Standard"},{"Description":"OTHER DISORDERS OF NERVOUS SYSTEM W MCC","Charge":"31953.18","Category":"Standard"},{"Description":"OTHER DISORDERS OF NERVOUS SYSTEM W CC","Charge":"6393.71","Category":"Standard"},{"Description":"OTHER DISORDERS OF NERVOUS SYSTEM W/O CC/MCC","Charge":"4612.82","Category":"Standard"},{"Description":"SEIZURES W MCC","Charge":"11342.61","Category":"Standard"},{"Description":"SEIZURES W/O MCC","Charge":"5671.68","Category":"Standard"},{"Description":"HEADACHES W/O MCC","Charge":"5337.03","Category":"Standard"},{"Description":" OTHER EAR, NOSE, MOUTH & THROAT O.R. PROCEDURES W CC/MCC","Charge":"13712.91","Category":"Standard"},{"Description":"DYSEQUILIBRIUM","Charge":"4570.35","Category":"Standard"},{"Description":"OTITIS MEDIA & URI W/O MCC","Charge":"5407.4","Category":"Standard"},{"Description":"MAJOR CHEST PROCEDURES W MCC","Charge":"40566.09","Category":"Standard"},{"Description":"OTHER RESP SYSTEM O.R. PROCEDURES W MCC","Charge":"24155.61","Category":"Standard"},{"Description":"OTHER RESP SYSTEM O.R. PROCEDURES W CC","Charge":"12925.14","Category":"Standard"},{"Description":"PULMONARY EMBOLISM W MCC","Charge":"11812.31","Category":"Standard"},{"Description":"PULMONARY EMBOLISM W/O MCC","Charge":"6802.19","Category":"Standard"},{"Description":"RESPIRATORY INFECTIONS & INFLAMMATIONS W CC","Charge":"9435.12","Category":"Standard"},{"Description":" ESOPHAGITIS, GASTROENT & MISC DIGEST DISORDERS W/O MCC","Charge":"5478.64","Category":"Standard"},{"Description":" ECMO OR TRACH W MV >96 HRS OR PDX EXC FACE, MOUTH & NECK W MAJ O.R.","Charge":"141667.41","Category":"Standard"},{"Description":"OTHER DIGESTIVE SYSTEM DIAGNOSES W CC","Charge":"6587.21","Category":"Standard"},{"Description":"Level 3 Neurostimulator and Related Procedures","Charge":"14743.66","Category":"DRG"},{"Description":"Level 1 Intraocular Procedures","Charge":"1360.45","Category":"DRG"},{"Description":"Level 2 Intraocular Procedures","Charge":"2551.0","Category":"DRG"},{"Description":"Level 3 Extraocular, Repair, and Plastic Eye Procedures","Charge":"1228.18","Category":"DRG"},{"Description":"Level 4 Extraocular, Repair, and Plastic Eye Procedures","Charge":"2059.48","Category":"DRG"},{"Description":"Comprehensive Observation Services","Charge":"1634.85","Category":"DRG"},{"Description":"ACUTE ADJUSTMENT REACTION & PSYCHOSOCIAL DYSFUNCTION","Charge":"4906.64","Category":"Standard"},{"Description":"SEPTICEMIA OR SEVERE SEPSIS W/O MV >96 HOURS W/O MCC","Charge":"6940.66","Category":"Standard"},{"Description":"SEPTICEMIA OR SEVERE SEPSIS W/O MV >96 HOURS W MCC","Charge":"13389.97","Category":"Standard"},{"Description":"SEPTICEMIA OR SEVERE SEPSIS W MV >96 HOURS","Charge":"43773.68","Category":"Standard"},{"Description":"VIRAL ILLNESS W/O MCC","Charge":"5464.86","Category":"Standard"},{"Description":"POSTOPERATIVE & POST","Charge":"7163.94","Category":"Standard"},{"Description":"POSTOPERATIVE & POST","Charge":"11191.94","Category":"Standard"},{"Description":"Level 2 Neurostimulator and Related Procedures","Charge":"4145.23","Category":"DRG"},{"Description":"POSTOPERATIVE OR POST","Charge":"14494.09","Category":"Standard"},{"Description":"INFECTIOUS & PARASITIC DISEASES W O.R. PROCEDURE W CC","Charge":"17457.57","Category":"Standard"},{"Description":"INFECTIOUS & PARASITIC DISEASES W O.R. PROCEDURE W MCC","Charge":"42589.5","Category":"Standard"},{"Description":"COAGULATION DISORDERS","Charge":"21109.29","Category":"Standard"},{"Description":"RED BLOOD CELL DISORDERS W/O MCC","Charge":"6411.57","Category":"Standard"},{"Description":"RED BLOOD CELL DISORDERS W MCC","Charge":"10475.04","Category":"Standard"},{"Description":"CESAREAN SECTION W CC/MCC","Charge":"8432.45","Category":"Standard"},{"Description":"OTHER KIDNEY & URINARY TRACT DIAGNOSES W CC","Charge":"7260.17","Category":"Standard"},{"Description":"OTHER KIDNEY & URINARY TRACT DIAGNOSES W MCC","Charge":"10968.63","Category":"Standard"},{"Description":"KIDNEY & URINARY TRACT SIGNS & SYMPTOMS W/O MCC","Charge":"5619.54","Category":"Standard"},{"Description":"URINARY STONES W/O ESW LITHOTRIPSY W/O MCC","Charge":"5473.62","Category":"Standard"},{"Description":"KIDNEY & URINARY TRACT INFECTIONS W/O MCC","Charge":"5654.75","Category":"Standard"},{"Description":"KIDNEY & URINARY TRACT INFECTIONS W MCC","Charge":"7274.67","Category":"Standard"},{"Description":"RENAL FAILURE W/O CC/MCC","Charge":"4289.0","Category":"Standard"},{"Description":"POSTOPERATIVE OR POST","Charge":"27960.58","Category":"Standard"},{"Description":"Level 2 Nerve Procedures","Charge":"3160.52","Category":"DRG"},{"Description":"Level 1 Nerve Procedures","Charge":"1139.73","Category":"DRG"},{"Description":"Level 5 Gynecologic Procedures","Charge":"2643.16","Category":"DRG"},{"Description":"NON","Charge":"11860.73","Category":"Standard"},{"Description":"NON","Charge":"26895.1","Category":"Standard"},{"Description":"EXTENSIVE O.R. PROCEDURE UNRELATED TO PRINCIPAL DIAGNOSIS W CC","Charge":"18814.79","Category":"Standard"},{"Description":"EXTENSIVE O.R. PROCEDURE UNRELATED TO PRINCIPAL DIAGNOSIS W MCC","Charge":"33110.72","Category":"Standard"},{"Description":"HIV W MAJOR RELATED CONDITION W MCC","Charge":"24674.92","Category":"Standard"},{"Description":"SIGNS & SYMPTOMS W/O MCC","Charge":"5891.48","Category":"Standard"},{"Description":"SIGNS & SYMPTOMS W MCC","Charge":"7542.5","Category":"Standard"},{"Description":"NON","Charge":"10724.73","Category":"Standard"},{"Description":"COMPLICATIONS OF TREATMENT W CC","Charge":"7457.73","Category":"Standard"},{"Description":"COMPLICATIONS OF TREATMENT W MCC","Charge":"15573.33","Category":"Standard"},{"Description":"POISONING & TOXIC EFFECTS OF DRUGS W/O MCC","Charge":"5491.67","Category":"Standard"},{"Description":"POISONING & TOXIC EFFECTS OF DRUGS W MCC","Charge":"9702.11","Category":"Standard"},{"Description":"ALCOHOL/DRUG ABUSE OR DEPENDENCE W/O REHABILITATION THERAPY W/O MCC","Charge":"5324.6","Category":"Standard"},{"Description":"ALCOHOL/DRUG ABUSE OR DEPENDENCE W/O REHABILITATION THERAPY W MCC","Charge":"11463.0","Category":"Standard"},{"Description":"ALCOHOL/DRUG ABUSE OR DEPENDENCE W REHABILITATION THERAPY","Charge":"9159.95","Category":"Standard"},{"Description":" ALCOHOL/DRUG ABUSE OR DEPENDENCE, LEFT AMA","Charge":"3848.79","Category":"Standard"},{"Description":"PSYCHOSES","Charge":"17117.54","Category":"Standard"},{"Description":"ORGANIC DISTURBANCES & INTELLECTUAL DISABILITY","Charge":"7841.88","Category":"Standard"},{"Description":"Level 5 Urology and Related Services","Charge":"2612.65","Category":"DRG"},{"Description":"Level 4 Urology and Related Services","Charge":"1813.47","Category":"DRG"},{"Description":"Level 3 Urology and Related Services","Charge":"1138.64","Category":"DRG"},{"Description":"Level 2 Laparoscopy and Related Services","Charge":"5338.33","Category":"DRG"},{"Description":"Level 1 Laparoscopy and Related Services","Charge":"3015.66","Category":"DRG"},{"Description":"Abdominal/Peritoneal/Biliary and Related Procedures","Charge":"2102.79","Category":"DRG"},{"Description":"Complex GI Procedures","Charge":"2853.96","Category":"DRG"},{"Description":"Level 3 Lower GI Procedures","Charge":"1524.68","Category":"DRG"},{"Description":"Level 6 Urology and Related Services","Charge":"5647.75","Category":"DRG"},{"Description":"Level 7 Urology and Related Services","Charge":"12365.92","Category":"DRG"},{"Description":"Level 4 Gynecologic Procedures","Charge":"1461.24","Category":"DRG"},{"Description":"RENAL FAILURE W CC","Charge":"6524.89","Category":"Standard"},{"Description":"RENAL FAILURE W MCC","Charge":"10124.88","Category":"Standard"},{"Description":"Level 4 Neurostimulator and Related Procedures","Charge":"23705.94","Category":"DRG"},{"Description":"KIDNEY TRANSPLANT","Charge":"25389.09","Category":"Standard"},{"Description":"SPINAL FUSION EXCEPT CERVICAL W/O MCC","Charge":"28101.93","Category":"Standard"},{"Description":" WND DEBRID & SKN GRFT EXC HAND, FOR MUSCULO","Charge":"37994.56","Category":"Standard"},{"Description":" WND DEBRID & SKN GRFT EXC HAND, FOR MUSCULO","Charge":"19487.71","Category":"Standard"},{"Description":"REVISION OF HIP OR KNEE REPLACEMENT W CC","Charge":"21071.29","Category":"Standard"},{"Description":"MAJOR HIP AND KNEE JOINT REPLACEMENT OR REATTACHMENT OF LOWER EXTREM","Charge":"17574.45","Category":"Standard"},{"Description":"MAJOR JOINT REPLACEMENT OR REATTACHMENT OF LOWER EXTREMITY W/O MCC","Charge":"12702.09","Category":"Standard"},{"Description":"CERVICAL SPINAL FUSION W MCC","Charge":"40548.75","Category":"Standard"},{"Description":"CERVICAL SPINAL FUSION W CC","Charge":"20901.38","Category":"Standard"},{"Description":"CERVICAL SPINAL FUSION W/O CC/MCC","Charge":"11527.71","Category":"Standard"},{"Description":"BIOPSIES OF MUSCULOSKELETAL SYSTEM & CONNECTIVE TISSUE W MCC","Charge":"21584.09","Category":"Standard"},{"Description":"HIP & FEMUR PROCEDURES EXCEPT MAJOR JOINT W MCC","Charge":"20897.96","Category":"Standard"},{"Description":"HIP & FEMUR PROCEDURES EXCEPT MAJOR JOINT W CC","Charge":"13531.41","Category":"Standard"},{"Description":"HIP & FEMUR PROCEDURES EXCEPT MAJOR JOINT W/O CC/MCC","Charge":"9683.17","Category":"Standard"},{"Description":"MAJOR JOINT/LIMB REATTACHMENT PROCEDURE OF UPPER EXTREMITIES","Charge":"15958.9","Category":"Standard"},{"Description":" LOWER EXTREM & HUMER PROC EXCEPT HIP,FOOT,FEMUR W MCC","Charge":"28911.91","Category":"Standard"},{"Description":"SPINAL FUSION EXCEPT CERVICAL W MCC","Charge":"42509.58","Category":"Standard"},{"Description":" LOWER EXTREM & HUMER PROC EXCEPT HIP,FOOT,FEMUR W CC","Charge":"14401.56","Category":"Standard"},{"Description":"SPINAL FUS EXC CERV W SPINAL CURV/MALIG/INFEC OR EXT FUS W CC","Charge":"57095.91","Category":"Standard"},{"Description":"SPINAL FUS EXC CERV W SPINAL CURV/MALIG/INFEC OR EXT FUS W MCC","Charge":"79165.64","Category":"Standard"},{"Description":"OTHER DIGESTIVE SYSTEM DIAGNOSES W/O CC/MCC","Charge":"5118.96","Category":"Standard"},{"Description":" PANCREAS, LIVER & SHUNT PROCEDURES W MCC","Charge":"39774.18","Category":"Standard"},{"Description":"LAPAROSCOPIC CHOLECYSTECTOMY W/O C.D.E. W MCC","Charge":"28420.55","Category":"Standard"},{"Description":"LAPAROSCOPIC CHOLECYSTECTOMY W/O C.D.E. W CC","Charge":"10672.24","Category":"Standard"},{"Description":"LAPAROSCOPIC CHOLECYSTECTOMY W/O C.D.E. W/O CC/MCC","Charge":"8840.5","Category":"Standard"},{"Description":"CIRRHOSIS & ALCOHOLIC HEPATITIS W MCC","Charge":"14487.52","Category":"Standard"},{"Description":"CIRRHOSIS & ALCOHOLIC HEPATITIS W CC","Charge":"7414.59","Category":"Standard"},{"Description":"DISORDERS OF PANCREAS EXCEPT MALIGNANCY W MCC","Charge":"12445.42","Category":"Standard"},{"Description":"DISORDERS OF PANCREAS EXCEPT MALIGNANCY W CC","Charge":"6544.16","Category":"Standard"},{"Description":"DISORDERS OF PANCREAS EXCEPT MALIGNANCY W/O CC/MCC","Charge":"4646.5","Category":"Standard"},{"Description":" DISORDERS OF LIVER EXCEPT MALIG,CIRR,ALC HEPA W MCC","Charge":"15716.23","Category":"Standard"},{"Description":" DISORDERS OF LIVER EXCEPT MALIG,CIRR,ALC HEPA W CC","Charge":"6947.4","Category":"Standard"},{"Description":" DISORDERS OF LIVER EXCEPT MALIG,CIRR,ALC HEPA W/O CC/MCC","Charge":"5287.5","Category":"Standard"},{"Description":"DISORDERS OF THE BILIARY TRACT W MCC","Charge":"17460.69","Category":"Standard"},{"Description":"DISORDERS OF THE BILIARY TRACT W CC","Charge":"6732.32","Category":"Standard"},{"Description":"KIDNEY & URETER PROCEDURES FOR NON","Charge":"30159.38","Category":"Standard"},{"Description":"SOFT TISSUE PROCEDURES W MCC","Charge":"19643.09","Category":"Standard"},{"Description":"OTHER DIGESTIVE SYSTEM DIAGNOSES W MCC","Charge":"11156.87","Category":"Standard"},{"Description":"OSTEOMYELITIS W MCC","Charge":"19161.18","Category":"Standard"},{"Description":" AMPUTAT OF LOWER LIMB FOR ENDOCRINE,NUTRIT,& METABOL DIS W CC","Charge":"13654.57","Category":"Standard"},{"Description":"SIGNS & SYMPTOMS OF MUSCULOSKELETAL SYSTEM & CONN TISSUE W/O MCC","Charge":"4994.92","Category":"Standard"},{"Description":" AFTERCARE, MUSCULOSKELETAL SYSTEM & CONNECTIVE TISSUE W CC","Charge":"7369.91","Category":"Standard"},{"Description":" MISC DISORDERS OF NUTRITION,METABOLISM,FLUIDS/ELECTROLYTES W/O MCC","Charge":"5088.89","Category":"Standard"},{"Description":" MISC DISORDERS OF NUTRITION,METABOLISM,FLUIDS/ELECTROLYTES W MCC","Charge":"8854.17","Category":"Standard"},{"Description":"DIABETES W CC","Charge":"6289.81","Category":"Standard"},{"Description":"DIABETES W MCC","Charge":"9335.22","Category":"Standard"},{"Description":" FX, SPRN, STRN & DISL EXCEPT FEMUR, HIP, PELVIS & THIGH W MCC","Charge":"13691.12","Category":"Standard"},{"Description":"OTHER MUSCULOSKELET SYS & CONN TISS O.R. PROC W CC","Charge":"17148.07","Category":"Standard"},{"Description":" OTHER ENDOCRINE, NUTRIT & METAB O.R. PROC W CC","Charge":"12994.64","Category":"Standard"},{"Description":"O.R. PROCEDURES FOR OBESITY W/O CC/MCC","Charge":"10119.76","Category":"Standard"},{"Description":" FX, SPRN, STRN & DISL EXCEPT FEMUR, HIP, PELVIS & THIGH W/O MCC","Charge":"5527.39","Category":"Standard"},{"Description":" OTHER SKIN, SUBCUT TISS & BREAST PROC W CC","Charge":"11704.77","Category":"Standard"},{"Description":"CELLULITIS W MCC","Charge":"11499.82","Category":"Standard"},{"Description":"CELLULITIS W/O MCC","Charge":"5867.52","Category":"Standard"},{"Description":" TRAUMA TO THE SKIN, SUBCUT TISS & BREAST W/O MCC","Charge":"6056.27","Category":"Standard"},{"Description":"MINOR SKIN DISORDERS W/O MCC","Charge":"5984.92","Category":"Standard"},{"Description":"BONE DISEASES & ARTHROPATHIES W/O MCC","Charge":"5448.44","Category":"Standard"},{"Description":"MEDICAL BACK PROBLEMS W/O MCC","Charge":"6086.07","Category":"Standard"},{"Description":"O.R. PROCEDURES FOR OBESITY W CC","Charge":"7915.54","Category":"Standard"},{"Description":"MEDICAL BACK PROBLEMS W MCC","Charge":"10792.81","Category":"Standard"},{"Description":"PATHOLOGICAL FRACTURES & MUSCULOSKELET & CONN TISS MALIG W CC","Charge":"8175.79","Category":"Standard"},{"Description":"CONNECTIVE TISSUE DISORDERS W CC","Charge":"8420.57","Category":"Standard"}]